{"entities":{"Q29165":{"pageid":32498,"ns":0,"title":"Q29165","lastrevid":1721547575,"modified":"2022-09-05T13:08:27Z","type":"item","id":"Q29165","labels":{"zh":{"language":"zh","value":"\u963f\u9ece\u535a\u91cc\u7701"},"pl":{"language":"pl","value":"Departament Alibori"},"eu":{"language":"eu","value":"Alibori"},"fr":{"language":"fr","value":"Alibori"},"ko":{"language":"ko","value":"\uc54c\ub9ac\ubcf4\ub9ac\uc8fc"},"es":{"language":"es","value":"Alibori"},"yo":{"language":"yo","value":"Ap\u00e1 Alibori"},"hu":{"language":"hu","value":"Alibori"},"it":{"language":"it","value":"dipartimento di Alibori"},"id":{"language":"id","value":"Departemen Alibori"},"de":{"language":"de","value":"Alibori"},"ja":{"language":"ja","value":"\u30a2\u30ea\u30dc\u30ea\u770c"},"br":{"language":"br","value":"Alibori"},"vi":{"language":"vi","value":"Alibori"},"en":{"language":"en","value":"Alibori Department"},"nl":{"language":"nl","value":"Alibori"},"sv":{"language":"sv","value":"Alibori"},"pt":{"language":"pt","value":"Alibori"},"tg":{"language":"tg","value":"\u0412\u0438\u043b\u043e\u044f\u0442\u0438 \u0410\u043b\u0438\u0431\u043e\u0440\u0438"},"ru":{"language":"ru","value":"\u0410\u043b\u0438\u0431\u043e\u0440\u0438"},"tr":{"language":"tr","value":"Alibori Departman\u0131"},"ro":{"language":"ro","value":"Departamentul Alibori"},"ca":{"language":"ca","value":"Alibori"},"fi":{"language":"fi","value":"Alibori"},"be-tarask":{"language":"be-tarask","value":"\u0410\u043b\u0456\u0431\u0430\u0440\u044b"},"bg":{"language":"bg","value":"\u0410\u043b\u0438\u0431\u043e\u0440\u0438"},"nb":{"language":"nb","value":"Alibori"},"fa":{"language":"fa","value":"\u0627\u0633\u062a\u0627\u0646 \u0622\u0644\u06cc\u0628\u0648\u0631\u06cc"},"da":{"language":"da","value":"Alibori"},"oc":{"language":"oc","value":"Alibori"},"lt":{"language":"lt","value":"Aliborio departamentas"},"ur":{"language":"ur","value":"\u0627\u0644\u06cc\u0628\u0648\u0631\u06cc \u0645\u062d\u06a9\u0645\u06c1"},"ceb":{"language":"ceb","value":"Alibori (departamento)"},"te":{"language":"te","value":"\u0c05\u0c32\u0c3f\u0c2c\u0c4b\u0c30\u0c3f \u0c21\u0c3f\u0c2a\u0c3e\u0c30\u0c4d\u0c1f\u0c4d\u0c2e\u0c46\u0c02\u0c1f\u0c4d"},"ar":{"language":"ar","value":"\u0625\u062f\u0627\u0631\u0629 \u0623\u0644\u064a\u0628\u0648\u0631\u064a"},"hi":{"language":"hi","value":"\u0905\u0932\u0940\u092c\u094b\u0930\u0940 \u0935\u093f\u092d\u093e\u0917"},"ms":{"language":"ms","value":"Alibori Department"},"th":{"language":"th","value":"\u0e40\u0e02\u0e15\u0e2d\u0e32\u0e25\u0e35\u0e42\u0e1a\u0e23\u0e35"},"ta":{"language":"ta","value":"\u0b85\u0bb2\u0bbf\u0baa\u0bcb\u0bb0\u0bbf \u0ba4\u0bc1\u0bb1\u0bc8"},"mr":{"language":"mr","value":"\u0905\u0932\u0940\u092c\u094b\u0930\u0940 \u0935\u093f\u092d\u093e\u0917"},"bn":{"language":"bn","value":"\u0986\u09b2\u09bf\u09ac\u09c1\u09b0\u09bf \u09ac\u09bf\u09ad\u09be\u0997"},"el":{"language":"el","value":"\u0391\u03bb\u03b9\u03bc\u03c0\u03bf\u03c1\u03af"},"si":{"language":"si","value":"\u0d87\u0dbd\u0dd2\u0db6\u0ddc\u0dbb\u0dd3 \u0daf\u0dd2\u0dc3\u0dca\u0dad\u0dca\u200d\u0dbb\u0dd2\u0d9a\u0dca\u0d9a\u0dba"},"gu":{"language":"gu","value":"\u0a85\u0ab2\u0abf\u0aac\u0acb \u0ab5\u0abf\u0aad\u0abe\u0a97"},"kn":{"language":"kn","value":"\u0c85\u0cb2\u0cbf\u0cac\u0ccb\u0cb0\u0cbf \u0c87\u0cb2\u0cbe\u0c96\u0cc6"},"uk":{"language":"uk","value":"\u0420\u0435\u0433\u0456\u043e\u043d \u0410\u043b\u0456\u0431\u043e\u0440\u0456"},"lv":{"language":"lv","value":"Alibori departaments"},"ast":{"language":"ast","value":"Alibori"},"frr":{"language":"frr","value":"Alibori Department"},"nan":{"language":"nan","value":"Alibori Ko\u0101n"},"az":{"language":"az","value":"Alibori departamenti"},"wuu":{"language":"wuu","value":"\u963f\u9ece\u535a\u91cc\u7701"},"he":{"language":"he","value":"\u05d0\u05dc\u05d9\u05d1\u05d5\u05e8\u05d9"},"sw":{"language":"sw","value":"Alibori"},"eo":{"language":"eo","value":"Departemento Alibori"}},"descriptions":{"nb":{"language":"nb","value":"departement i Benin"},"it":{"language":"it","value":"dipartimento beninese"},"es":{"language":"es","value":"departamento de Ben\u00edn"},"en":{"language":"en","value":"department of Benin"},"de":{"language":"de","value":"D\u00e9partement von Benin"},"fr":{"language":"fr","value":"d\u00e9partement du B\u00e9nin"},"el":{"language":"el","value":"\u03bd\u03bf\u03bc\u03cc\u03c2 \u03c4\u03bf\u03c5 \u039c\u03c0\u03b5\u03bd\u03af\u03bd"},"fa":{"language":"fa","value":"\u0628\u062e\u0634\u06cc (\u062f\u067e\u0627\u0631\u062a\u0645\u0627\u0646) \u062f\u0631 \u0628\u0646\u06cc\u0646"},"eu":{"language":"eu","value":"Beningo departamendua"},"ar":{"language":"ar","value":"\u0645\u0642\u0627\u0637\u0639\u0629"}},"aliases":{"es":[{"language":"es","value":"Alibori Department"}],"yo":[{"language":"yo","value":"Alibori Department"}],"it":[{"language":"it","value":"Alibori"}],"id":[{"language":"id","value":"Alibori"}],"de":[{"language":"de","value":"BJ-AL"}],"bg":[{"language":"bg","value":"\u0414\u0435\u043f\u0430\u0440\u0442\u0430\u043c\u0435\u043d\u0442 \u0410\u043b\u0438\u0431\u043e\u0440\u0438"}],"te":[{"language":"te","value":"\u0c05\u0c32\u0c3f\u0c2c\u0c4b\u0c30\u0c3f \u0c35\u0c3f\u0c2d\u0c3e\u0c17\u0c02"}],"ur":[{"language":"ur","value":"\u0627\u0644\u06cc\u0628\u0648\u0631\u06cc \u0688\u06cc\u067e\u0627\u0631\u0679\u0645\u0646\u0679"}]},"claims":{"P17":[{"mainsnak":{"snaktype":"value","property":"P17","hash":"91cd5d67276cbbdf204d689ae1996b3cd60c65b4","datavalue":{"value":{"entity-type":"item","numeric-id":962,"id":"Q962"},"type":"wikibase-entityid"},"datatype":"wikibase-item"},"type":"statement","id":"q29165$14FEC29D-C060-4F62-9475-55850714FAD3","rank":"normal","references":[{"hash":"288ab581e7d2d02995a26dfa8b091d96e78457fc","snaks":{"P143":[{"snaktype":"value","property":"P143","hash":"6a164248fc96bfa583bbb495cb63ae6401ec203c","datavalue":{"value":{"entity-type":"item","numeric-id":206855,"id":"Q206855"},"type":"wikibase-entityid"},"datatype":"wikibase-item"}]},"snaks-order":["P143"]}]}],"P36":[{"mainsnak":{"snaktype":"value","property":"P36","hash":"35b9658013190946fb613b8b674e963643dbc5f3","datavalue":{"value":{"entity-type":"item","numeric-id":845666,"id":"Q845666"},"type":"wikibase-entityid"},"datatype":"wikibase-item"},"type":"statement","id":"q29165$C6D67BCB-CFF5-4CF3-9BB9-41BE1EA2B9C7","rank":"normal"}],"P47":[{"mainsnak":{"snaktype":"value","property":"P47","hash":"4c9f284e6e66eec7cd9c4751929917f37aa7bd3f","datavalue":{"value":{"entity-type":"item","numeric-id":29154,"id":"Q29154"},"type":"wikibase-entityid"},"datatype":"wikibase-item"},"type":"statement","id":"q29165$CB6E9445-52FB-4B7A-838F-83B862469CFB","rank":"normal"},{"mainsnak":{"snaktype":"value","property":"P47","hash":"8b3ff72f930b1232e2122b0da6ca05afe482aefd","datavalue":{"value":{"entity-type":"item","numeric-id":29136,"id":"Q29136"},"type":"wikibase-entityid"},"datatype":"wikibase-item"},"type":"statement","id":"q29165$4C453B96-0198-418D-AAF9-DDEFE828AC1C","rank":"normal"}],"P300":[{"mainsnak":{"snaktype":"value","property":"P300","hash":"3621e30bfb7fb43117dcf46d33ff152a03640861","datavalue":{"value":"BJ-AL","type":"string"},"datatype":"external-id"},"type":"statement","id":"q29165$AD930944-663A-4220-A404-3B2F1122744E","rank":"normal"}],"P625":[{"mainsnak":{"snaktype":"value","property":"P625","hash":"4d4fc14dca9b4a2836f1f5901dc8399771374379","datavalue":{"value":{"latitude":11.128611,"longitude":2.936944,"altitude":null,"precision":1.0e-5,"globe":"http://www.wikidata.org/entity/Q2"},"type":"globecoordinate"},"datatype":"globe-coordinate"},"type":"statement","id":"q29165$7DEF788B-C109-43B6-BD4A-4F87C3F2C894","rank":"normal","references":[{"hash":"732ec1c90a6f0694c7db9a71bf09fe7f2b674172","snaks":{"P143":[{"snaktype":"value","property":"P143","hash":"9123b0de1cc9c3954366ba797d598e4e1ea4146f","datavalue":{"value":{"entity-type":"item","numeric-id":10000,"id":"Q10000"},"type":"wikibase-entityid"},"datatype":"wikibase-item"}]},"snaks-order":["P143"]}]}],"P131":[{"mainsnak":{"snaktype":"value","property":"P131","hash":"2c533d9be33483497ddad5f8b604bb30ee6ecc32","datavalue":{"value":{"entity-type":"item","numeric-id":962,"id":"Q962"},"type":"wikibase-entityid"},"datatype":"wikibase-item"},"type":"statement","id":"q29165$781655C0-8703-4D7F-99DC-E301F91CBE72","rank":"normal","references":[{"hash":"d5847b9b6032aa8b13dae3c2dfd9ed5d114d21b3","snaks":{"P143":[{"snaktype":"value","property":"P143","hash":"5a343e7e758a4282a01316d3e959b6e653b767fc","datavalue":{"value":{"entity-type":"item","numeric-id":11920,"id":"Q11920"},"type":"wikibase-entityid"},"datatype":"wikibase-item"}]},"snaks-order":["P143"]}]}],"P150":[{"mainsnak":{"snaktype":"value","property":"P150","hash":"fae9525b669f4d2b5eec94d4a8132a8927731fcf","datavalue":{"value":{"entity-type":"item","numeric-id":2200458,"id":"Q2200458"},"type":"wikibase-entityid"},"datatype":"wikibase-item"},"type":"statement","id":"q29165$2A1080F4-E5C7-40EE-95D7-95695C62FE0F","rank":"normal","references":[{"hash":"d5847b9b6032aa8b13dae3c2dfd9ed5d114d21b3","snaks":{"P143":[{"snaktype":"value","property":"P143","hash":"5a343e7e758a4282a01316d3e959b6e653b767fc","datavalue":{"value":{"entity-type":"item","numeric-id":11920,"id":"Q11920"},"type":"wikibase-entityid"},"datatype":"wikibase-item"}]},"snaks-order":["P143"]}]},{"mainsnak":{"snaktype":"value","property":"P150","hash":"dedc3a5c7eb68974a6c20e1c84d42ad4638e3a5b","datavalue":{"value":{"entity-type":"item","numeric-id":583110,"id":"Q583110"},"type":"wikibase-entityid"},"datatype":"wikibase-item"},"type":"statement","id":"q29165$1B720CD4-6D7D-404F-AAB1-1059446921F4","rank":"normal","references":[{"hash":"d5847b9b6032aa8b13dae3c2dfd9ed5d114d21b3","snaks":{"P143":[{"snaktype":"value","property":"P143","hash":"5a343e7e758a4282a01316d3e959b6e653b767fc","datavalue":{"value":{"entity-type":"item","numeric-id":11920,"id":"Q11920"},"type":"wikibase-entityid"},"datatype":"wikibase-item"}]},"snaks-order":["P143"]}]},{"mainsnak":{"snaktype":"value","property":"P150","hash":"db18592729209da0645fe87e12c8621daaabb918","datavalue":{"value":{"entity-type":"item","numeric-id":845666,"id":"Q845666"},"type":"wikibase-entityid"},"datatype":"wikibase-item"},"type":"statement","id":"q29165$AAF7FB1C-7E36-4311-8045-322B72AD3B50","rank":"normal","references":[{"hash":"d5847b9b6032aa8b13dae3c2dfd9ed5d114d21b3","snaks":{"P143":[{"snaktype":"value","property":"P143","hash":"5a343e7e758a4282a01316d3e959b6e653b767fc","datavalue":{"value":{"entity-type":"item","numeric-id":11920,"id":"Q11920"},"type":"wikibase-entityid"},"datatype":"wikibase-item"}]},"snaks-order":["P143"]}]},{"mainsnak":{"snaktype":"value","property":"P150","hash":"731fac79b67ab66127f77bc10475af027321734c","datavalue":{"value":{"entity-type":"item","numeric-id":1860831,"id":"Q1860831"},"type":"wikibase-entityid"},"datatype":"wikibase-item"},"type":"statement","id":"q29165$3047B363-A503-4B4F-B529-BE1FD2BF8A3E","rank":"normal","references":[{"hash":"d5847b9b6032aa8b13dae3c2dfd9ed5d114d21b3","snaks":{"P143":[{"snaktype":"value","property":"P143","hash":"5a343e7e758a4282a01316d3e959b6e653b767fc","datavalue":{"value":{"entity-type":"item","numeric-id":11920,"id":"Q11920"},"type":"wikibase-entityid"},"datatype":"wikibase-item"}]},"snaks-order":["P143"]}]},{"mainsnak":{"snaktype":"value","property":"P150","hash":"c9e93fa0c620e5937f741d8e2f710b0c534e03a4","datavalue":{"value":{"entity-type":"item","numeric-id":2337446,"id":"Q2337446"},"type":"wikibase-entityid"},"datatype":"wikibase-item"},"type":"statement","id":"q29165$9951EF81-FEDA-4422-80F8-E14504C6A8C3","rank":"normal","references":[{"hash":"d5847b9b6032aa8b13dae3c2dfd9ed5d114d21b3","snaks":{"P143":[{"snaktype":"value","property":"P143","hash":"5a343e7e758a4282a01316d3e959b6e653b767fc","datavalue":{"value":{"entity-type":"item","numeric-id":11920,"id":"Q11920"},"type":"wikibase-entityid"},"datatype":"wikibase-item"}]},"snaks-order":["P143"]}]},{"mainsnak":{"snaktype":"value","property":"P150","hash":"15159ee298f7da6761f329bfe390288461788ea0","datavalue":{"value":{"entity-type":"item","numeric-id":2202003,"id":"Q2202003"},"type":"wikibase-entityid"},"datatype":"wikibase-item"},"type":"statement","id":"q29165$7040B104-E95B-4A0F-B7A3-3CC981C7EB1B","rank":"normal","references":[{"hash":"d5847b9b6032aa8b13dae3c2dfd9ed5d114d21b3","snaks":{"P143":[{"snaktype":"value","property":"P143","hash":"5a343e7e758a4282a01316d3e959b6e653b767fc","datavalue":{"value":{"entity-type":"item","numeric-id":11920,"id":"Q11920"},"type":"wikibase-entityid"},"datatype":"wikibase-item"}]},"snaks-order":["P143"]}]}],"P910":[{"mainsnak":{"snaktype":"value","property":"P910","hash":"7b25676f3a54641e5db8f9a307640e6353f7705c","datavalue":{"value":{"entity-type":"item","numeric-id":8235251,"id":"Q8235251"},"type":"wikibase-entityid"},"datatype":"wikibase-item"},"type":"statement","id":"Q29165$F158E595-AAC7-432D-9344-CBC5AEAE2536","rank":"normal"}],"P31":[{"mainsnak":{"snaktype":"value","property":"P31","hash":"bfc708db47d7a2d9f13546a82a958dab9f02abef","datavalue":{"value":{"entity-type":"item","numeric-id":792929,"id":"Q792929"},"type":"wikibase-entityid"},"datatype":"wikibase-item"},"type":"statement","id":"Q29165$7D27F89E-5B1B-4E22-811E-5E1199F90954","rank":"normal"}],"P646":[{"mainsnak":{"snaktype":"value","property":"P646","hash":"18beb20492eaafa042a754ee9d4db54e5389c643","datavalue":{"value":"/m/02lm_z","type":"string"},"datatype":"external-id"},"type":"statement","id":"Q29165$A6AE14A6-E7D0-43CD-9E4E-932B62CC54B9","rank":"normal","references":[{"hash":"2b00cb481cddcac7623114367489b5c194901c4a","snaks":{"P248":[{"snaktype":"value","property":"P248","hash":"a94b740202b097dd33355e0e6c00e54b9395e5e0","datavalue":{"value":{"entity-type":"item","numeric-id":15241312,"id":"Q15241312"},"type":"wikibase-entityid"},"datatype":"wikibase-item"}],"P577":[{"snaktype":"value","property":"P577","hash":"fde79ecb015112d2f29229ccc1ec514ed3e71fa2","datavalue":{"value":{"time":"+2013-10-28T00:00:00Z","timezone":0,"before":0,"after":0,"precision":11,"calendarmodel":"http://www.wikidata.org/entity/Q1985727"},"type":"time"},"datatype":"time"}]},"snaks-order":["P248","P577"]}]}],"P901":[{"mainsnak":{"snaktype":"value","property":"P901","hash":"b36747d89ecd69eb74d8801d04b1c428feed0774","datavalue":{"value":"BN07","type":"string"},"datatype":"external-id"},"type":"statement","id":"Q29165$F34B8471-ECCD-4B53-ACDF-20B6E3B44951","rank":"normal","references":[{"hash":"7bafa48f7ec25d0199c2fbf8201e96bb54cdfd17","snaks":{"P143":[{"snaktype":"value","property":"P143","hash":"e4f6d9441d0600513c4533c672b5ab472dc73694","datavalue":{"value":{"entity-type":"item","numeric-id":328,"id":"Q328"},"type":"wikibase-entityid"},"datatype":"wikibase-item"}],"P4656":[{"snaktype":"value","property":"P4656","hash":"bbb405b2b1ab89d1f5289d5162c24a57cfc23287","datavalue":{"value":"https://en.wikipedia.org/w/index.php?title=List_of_FIPS_region_codes_(A%E2%80%93C)&oldid=551304616","type":"string"},"datatype":"url"}],"P407":[{"snaktype":"value","property":"P407","hash":"daf1c4fcb58181b02dff9cc89deb084004ddae4b","datavalue":{"value":{"entity-type":"item","numeric-id":1860,"id":"Q1860"},"type":"wikibase-entityid"},"datatype":"wikibase-item"}],"P813":[{"snaktype":"value","property":"P813","hash":"14b9dff5c416dff33edad44dec13b87306ffc1cd","datavalue":{"value":{"time":"+2013-12-30T00:00:00Z","timezone":0,"before":0,"after":0,"precision":11,"calendarmodel":"http://www.wikidata.org/entity/Q1985727"},"type":"time"},"datatype":"time"}],"P1476":[{"snaktype":"value","property":"P1476","hash":"a9f9118d4e355bc034b38459da529958c5fcb4b7","datavalue":{"value":{"text":"List of FIPS region codes (A-C)","language":"en"},"type":"monolingualtext"},"datatype":"monolingualtext"}]},"snaks-order":["P143","P4656","P407","P813","P1476"]}]}],"P1566":[{"mainsnak":{"snaktype":"value","property":"P1566","hash":"82a3a2d11c6b12b1ae9d6ec98b59b8094615fef7","datavalue":{"value":"2597271","type":"string"},"datatype":"external-id"},"type":"statement","id":"Q29165$D07849E8-2B4B-4746-A0D5-AF52CD6F17F5","rank":"normal","references":[{"hash":"88694a0f4d1486770c269f7db16a1982f74da69d","snaks":{"P248":[{"snaktype":"value","property":"P248","hash":"1b3ef912a2bd61e18dd43abd184337eb010b2e96","datavalue":{"value":{"entity-type":"item","numeric-id":830106,"id":"Q830106"},"type":"wikibase-entityid"},"datatype":"wikibase-item"}]},"snaks-order":["P248"]}]}],"P571":[{"mainsnak":{"snaktype":"value","property":"P571","hash":"9a2407752b31cc1be83a39879c73a80d9ab7b009","datavalue":{"value":{"time":"+1999-00-00T00:00:00Z","timezone":0,"before":0,"after":0,"precision":9,"calendarmodel":"http://www.wikidata.org/entity/Q1985727"},"type":"time"},"datatype":"time"},"type":"statement","id":"Q29165$B3B30873-41D9-4470-ADAF-038FF2077D1A","rank":"normal","references":[{"hash":"fa278ebfc458360e5aed63d5058cca83c46134f1","snaks":{"P143":[{"snaktype":"value","property":"P143","hash":"e4f6d9441d0600513c4533c672b5ab472dc73694","datavalue":{"value":{"entity-type":"item","numeric-id":328,"id":"Q328"},"type":"wikibase-entityid"},"datatype":"wikibase-item"}]},"snaks-order":["P143"]}]}],"P2046":[{"mainsnak":{"snaktype":"value","property":"P2046","hash":"d81f59d80d8dc813741a78a809906d4bcbc55289","datavalue":{"value":{"amount":"+26242.0","unit":"http://www.wikidata.org/entity/Q712226"},"type":"quantity"},"datatype":"quantity"},"type":"statement","id":"Q29165$BE92C270-1267-4E97-BEA7-8DE16292F6A6","rank":"normal","references":[{"hash":"8f08ac3e0839bdbc4c6eb8d671e772deb12ba423","snaks":{"P143":[{"snaktype":"value","property":"P143","hash":"250b03083f7971a02473af3e43115ef521b1440d","datavalue":{"value":{"entity-type":"item","numeric-id":465,"id":"Q465"},"type":"wikibase-entityid"},"datatype":"wikibase-item"}]},"snaks-order":["P143"]}]}],"P856":[{"mainsnak":{"snaktype":"value","property":"P856","hash":"fcaaad8f4309e899ec6421e797c77e5f914b65e9","datavalue":{"value":"http://www.gouv.bj/departements/le-departement-de-lalibori-et-ses-communes","type":"string"},"datatype":"url"},"type":"statement","id":"Q29165$C6F19DB8-2A97-4D98-83DD-3F591DDE72FA","rank":"normal","references":[{"hash":"d4bd87b862b12d99d26e86472d44f26858dee639","snaks":{"P143":[{"snaktype":"value","property":"P143","hash":"f30cbd35620c4ea6d0633aaf0210a8916130469b","datavalue":{"value":{"entity-type":"item","numeric-id":8447,"id":"Q8447"},"type":"wikibase-entityid"},"datatype":"wikibase-item"}]},"snaks-order":["P143"]}]}],"P242":[{"mainsnak":{"snaktype":"value","property":"P242","hash":"dc753d8dbf64c84c48f210f159e975dffb3eee8a","datavalue":{"value":"Benin - Alibori.svg","type":"string"},"datatype":"commonsMedia"},"type":"statement","id":"Q29165$BBA6BE9D-21EA-48AD-86B3-D970A9A25B98","rank":"normal","references":[{"hash":"e71a7903858496c67eea189a7084d5559f788edb","snaks":{"P143":[{"snaktype":"value","property":"P143","hash":"5d3b16d350189b0a81818758208505444c86c127","datavalue":{"value":{"entity-type":"item","numeric-id":565,"id":"Q565"},"type":"wikibase-entityid"},"datatype":"wikibase-item"}]},"snaks-order":["P143"]}]}],"P373":[{"mainsnak":{"snaktype":"value","property":"P373","hash":"f93d947e24fb1896e121c0a05aee8d3dbb98cc40","datavalue":{"value":"Alibori Department","type":"string"},"datatype":"string"},"type":"statement","id":"Q29165$7ECCB345-C1B3-4DA0-ACFD-0CDE3C8CFC8B","rank":"normal"}],"P1667":[{"mainsnak":{"snaktype":"value","property":"P1667","hash":"7c2f9a9370ef6466e6c3bfae0cf3e8152176a1f6","datavalue":{"value":"7032091","type":"string"},"datatype":"external-id"},"type":"statement","id":"Q29165$60CE8519-BECD-4E9C-9DEA-984BDD386BCF","rank":"normal"}],"P18":[{"mainsnak":{"snaktype":"value","property":"P18","hash":"9207796f212f28be587f5b62bffedd4d4eaa915a","datavalue":{"value":"Rice cultivation in Benin - panoramio - Africa Rice Center (12).jpg","type":"string"},"datatype":"commonsMedia"},"type":"statement","id":"Q29165$AEAB9061-84DE-47FB-8FE2-B905C4FD42D0","rank":"normal","references":[{"hash":"8379f84896b7e03dfba802ffd6177322e2723270","snaks":{"P143":[{"snaktype":"value","property":"P143","hash":"e4f6d9441d0600513c4533c672b5ab472dc73694","datavalue":{"value":{"entity-type":"item","numeric-id":328,"id":"Q328"},"type":"wikibase-entityid"},"datatype":"wikibase-item"}],"P4656":[{"snaktype":"value","property":"P4656","hash":"213cf3b7781b7aee9433c4f3b044f8d7965e590d","datavalue":{"value":"https://en.wikipedia.org/w/index.php?title=Alibori_Department&oldid=846953687","type":"string"},"datatype":"url"}]},"snaks-order":["P143","P4656"]}]}],"P2936":[{"mainsnak":{"snaktype":"value","property":"P2936","hash":"d4b2187de461757323b0ad1c9ddcb77347511675","datavalue":{"value":{"entity-type":"item","numeric-id":3913304,"id":"Q3913304"},"type":"wikibase-entityid"},"datatype":"wikibase-item"},"type":"statement","id":"Q29165$0622EFD8-2104-4E64-81D9-575CF828F2DC","rank":"normal"},{"mainsnak":{"snaktype":"value","property":"P2936","hash":"a9a3e07e6fc5bf89e1af32b08a46b37e47915527","datavalue":{"value":{"entity-type":"item","numeric-id":35164,"id":"Q35164"},"type":"wikibase-entityid"},"datatype":"wikibase-item"},"type":"statement","id":"Q29165$13B42334-297D-4B69-8C8B-A67167CCA094","rank":"normal"},{"mainsnak":{"snaktype":"value","property":"P2936","hash":"c0d4fa8cdc2758c5865cf9635e185682487bb071","datavalue":{"value":{"entity-type":"item","numeric-id":35474,"id":"Q35474"},"type":"wikibase-entityid"},"datatype":"wikibase-item"},"type":"statement","id":"Q29165$A73E443E-5EF5-4F13-AB5E-D3025E40AE7B","rank":"normal"},{"mainsnak":{"snaktype":"value","property":"P2936","hash":"0f34096c7f05075cf1c2fc0e773c789f647ca2a0","datavalue":{"value":{"entity-type":"item","numeric-id":36047,"id":"Q36047"},"type":"wikibase-entityid"},"datatype":"wikibase-item"},"type":"statement","id":"Q29165$CB878518-1A97-448D-B8B7-FDF3010833CE","rank":"normal"},{"mainsnak":{"snaktype":"value","property":"P2936","hash":"4291ebb2d9206a5e772cf96792059343f6a774f5","datavalue":{"value":{"entity-type":"item","numeric-id":34889,"id":"Q34889"},"type":"wikibase-entityid"},"datatype":"wikibase-item"},"type":"statement","id":"Q29165$15A272D0-E4CC-4019-A772-6D997D745EA6","rank":"normal"},{"mainsnak":{"snaktype":"value","property":"P2936","hash":"86e003b58573ba20d996583028ffb5042a223f01","datavalue":{"value":{"entity-type":"item","numeric-id":12952430,"id":"Q12952430"},"type":"wikibase-entityid"},"datatype":"wikibase-item"},"type":"statement","id":"Q29165$7C2C82BF-9C26-4E1C-B9D4-3CB0FD25A549","rank":"normal"},{"mainsnak":{"snaktype":"value","property":"P2936","hash":"446734dc518f786441ae7008b6d7297bdd93f051","datavalue":{"value":{"entity-type":"item","numeric-id":34983,"id":"Q34983"},"type":"wikibase-entityid"},"datatype":"wikibase-item"},"type":"statement","id":"Q29165$1EF4E020-DA7D-42D6-A3D9-05C5A4026583","rank":"normal"}],"P6766":[{"mainsnak":{"snaktype":"value","property":"P6766","hash":"bf84333bfe03ece2994cd6d424513e25a017349f","datavalue":{"value":"85668805","type":"string"},"datatype":"external-id"},"type":"statement","id":"Q29165$FD0FBF03-4BC7-4102-A6B1-96037059A38C","rank":"normal"}],"P3896":[{"mainsnak":{"snaktype":"value","property":"P3896","hash":"ae682e69a1eb55f5dc79be2cfc54108ff510f7b4","datavalue":{"value":"Data:Benin/Alibori.map","type":"string"},"datatype":"geo-shape"},"type":"statement","id":"Q29165$6F218E78-9E01-4ACB-8F9F-B4E197586732","rank":"normal"}],"P7471":[{"mainsnak":{"snaktype":"value","property":"P7471","hash":"f9c9e7fa1c69d6550651c890aea33be35d928618","datavalue":{"value":"11325","type":"string"},"datatype":"external-id"},"type":"statement","id":"Q29165$FBA276C5-CF48-4435-A799-9C6F058217BB","rank":"normal","references":[{"hash":"cd265fa9f8591b5905bba6f0b4fd1d62328dc775","snaks":{"P248":[{"snaktype":"value","property":"P248","hash":"c2f50f16b9b3f2fb15e6f376ad31872737d27fc1","datavalue":{"value":{"entity-type":"item","numeric-id":16958215,"id":"Q16958215"},"type":"wikibase-entityid"},"datatype":"wikibase-item"}],"P813":[{"snaktype":"value","property":"P813","hash":"4cc18df9c2293cccb3c32fe5fa19a669b1875932","datavalue":{"value":{"time":"+2021-04-25T00:00:00Z","timezone":0,"before":0,"after":0,"precision":11,"calendarmodel":"http://www.wikidata.org/entity/Q1985727"},"type":"time"},"datatype":"time"}],"P854":[{"snaktype":"value","property":"P854","hash":"f41baedd414e0500ea077cc9f6af295ff25e1d30","datavalue":{"value":"https://www.inaturalist.org/places/inaturalist-places.csv.zip","type":"string"},"datatype":"url"}]},"snaks-order":["P248","P813","P854"]}]}],"P269":[{"mainsnak":{"snaktype":"value","property":"P269","hash":"6c0f81a71c65696d240050715e7a0606e70c2f41","datavalue":{"value":"220232512","type":"string"},"datatype":"external-id"},"type":"statement","id":"Q29165$a216d886-449a-5476-7778-f8c5a3f79c53","rank":"normal"}],"P214":[{"mainsnak":{"snaktype":"value","property":"P214","hash":"c353b395423100e4db4f72d9d1bb0ea2d53c5086","datavalue":{"value":"3006151304653249460004","type":"string"},"datatype":"external-id"},"type":"statement","id":"Q29165$c3c91bd4-4512-6287-a177-3681b5b110a1","rank":"normal"}]},"sitelinks":{"arwiki":{"site":"arwiki","title":"\u0625\u062f\u0627\u0631\u0629 \u0623\u0644\u064a\u0628\u0648\u0631\u064a","badges":[],"url":"https://ar.wikipedia.org/wiki/%D8%A5%D8%AF%D8%A7%D8%B1%D8%A9_%D8%A3%D9%84%D9%8A%D8%A8%D9%88%D8%B1%D9%8A"},"astwiki":{"site":"astwiki","title":"Alibori","badges":[],"url":"https://ast.wikipedia.org/wiki/Alibori"},"azwiki":{"site":"azwiki","title":"Alibori departamenti","badges":[],"url":"https://az.wikipedia.org/wiki/Alibori_departamenti"},"be_x_oldwiki":{"site":"be_x_oldwiki","title":"\u0410\u043b\u0456\u0431\u0430\u0440\u044b","badges":[],"url":"https://be-tarask.wikipedia.org/wiki/%D0%90%D0%BB%D1%96%D0%B1%D0%B0%D1%80%D1%8B"},"bgwiki":{"site":"bgwiki","title":"\u0410\u043b\u0438\u0431\u043e\u0440\u0438 (\u0434\u0435\u043f\u0430\u0440\u0442\u0430\u043c\u0435\u043d\u0442)","badges":[],"url":"https://bg.wikipedia.org/wiki/%D0%90%D0%BB%D0%B8%D0%B1%D0%BE%D1%80%D0%B8_(%D0%B4%D0%B5%D0%BF%D0%B0%D1%80%D1%82%D0%B0%D0%BC%D0%B5%D0%BD%D1%82)"},"brwiki":{"site":"brwiki","title":"Alibori","badges":[],"url":"https://br.wikipedia.org/wiki/Alibori"},"cawiki":{"site":"cawiki","title":"Alibori","badges":[],"url":"https://ca.wikipedia.org/wiki/Alibori"},"cebwiki":{"site":"cebwiki","title":"Alibori (departamento)","badges":[],"url":"https://ceb.wikipedia.org/wiki/Alibori_(departamento)"},"dawiki":{"site":"dawiki","title":"Alibori","badges":[],"url":"https://da.wikipedia.org/wiki/Alibori"},"dewiki":{"site":"dewiki","title":"Alibori","badges":[],"url":"https://de.wikipedia.org/wiki/Alibori"},"enwiki":{"site":"enwiki","title":"Alibori Department","badges":[],"url":"https://en.wikipedia.org/wiki/Alibori_Department"},"eowiki":{"site":"eowiki","title":"Departemento Alibori","badges":[],"url":"https://eo.wikipedia.org/wiki/Departemento_Alibori"},"eswiki":{"site":"eswiki","title":"Departamento de Alibori","badges":[],"url":"https://es.wikipedia.org/wiki/Departamento_de_Alibori"},"euwiki":{"site":"euwiki","title":"Alibori","badges":[],"url":"https://eu.wikipedia.org/wiki/Alibori"},"fawiki":{"site":"fawiki","title":"\u0627\u0633\u062a\u0627\u0646 \u0622\u0644\u06cc\u0628\u0648\u0631\u06cc","badges":[],"url":"https://fa.wikipedia.org/wiki/%D8%A7%D8%B3%D8%AA%D8%A7%D9%86_%D8%A2%D9%84%DB%8C%D8%A8%D9%88%D8%B1%DB%8C"},"fiwiki":{"site":"fiwiki","title":"Alibori","badges":[],"url":"https://fi.wikipedia.org/wiki/Alibori"},"frrwiki":{"site":"frrwiki","title":"Alibori Department","badges":[],"url":"https://frr.wikipedia.org/wiki/Alibori_Department"},"frwiki":{"site":"frwiki","title":"Alibori","badges":[],"url":"https://fr.wikipedia.org/wiki/Alibori"},"huwiki":{"site":"huwiki","title":"Alibori","badges":[],"url":"https://hu.wikipedia.org/wiki/Alibori"},"idwiki":{"site":"idwiki","title":"Departemen Alibori","badges":[],"url":"https://id.wikipedia.org/wiki/Departemen_Alibori"},"itwiki":{"site":"itwiki","title":"Dipartimento di Alibori","badges":[],"url":"https://it.wikipedia.org/wiki/Dipartimento_di_Alibori"},"jawiki":{"site":"jawiki","title":"\u30a2\u30ea\u30dc\u30ea\u770c","badges":[],"url":"https://ja.wikipedia.org/wiki/%E3%82%A2%E3%83%AA%E3%83%9C%E3%83%AA%E7%9C%8C"},"kowiki":{"site":"kowiki","title":"\uc54c\ub9ac\ubcf4\ub9ac\uc8fc","badges":[],"url":"https://ko.wikipedia.org/wiki/%EC%95%8C%EB%A6%AC%EB%B3%B4%EB%A6%AC%EC%A3%BC"},"ltwiki":{"site":"ltwiki","title":"Aliborio departamentas","badges":[],"url":"https://lt.wikipedia.org/wiki/Aliborio_departamentas"},"nlwiki":{"site":"nlwiki","title":"Alibori","badges":[],"url":"https://nl.wikipedia.org/wiki/Alibori"},"nowiki":{"site":"nowiki","title":"Alibori","badges":[],"url":"https://no.wikipedia.org/wiki/Alibori"},"plwiki":{"site":"plwiki","title":"Departament Alibori","badges":[],"url":"https://pl.wikipedia.org/wiki/Departament_Alibori"},"ptwiki":{"site":"ptwiki","title":"Alibori","badges":[],"url":"https://pt.wikipedia.org/wiki/Alibori"},"rowiki":{"site":"rowiki","title":"Departamentul Alibori","badges":[],"url":"https://ro.wikipedia.org/wiki/Departamentul_Alibori"},"ruwiki":{"site":"ruwiki","title":"\u0410\u043b\u0438\u0431\u043e\u0440\u0438 (\u0434\u0435\u043f\u0430\u0440\u0442\u0430\u043c\u0435\u043d\u0442)","badges":[],"url":"https://ru.wikipedia.org/wiki/%D0%90%D0%BB%D0%B8%D0%B1%D0%BE%D1%80%D0%B8_(%D0%B4%D0%B5%D0%BF%D0%B0%D1%80%D1%82%D0%B0%D0%BC%D0%B5%D0%BD%D1%82)"},"simplewiki":{"site":"simplewiki","title":"Alibori Department","badges":[],"url":"https://simple.wikipedia.org/wiki/Alibori_Department"},"svwiki":{"site":"svwiki","title":"Alibori","badges":[],"url":"https://sv.wikipedia.org/wiki/Alibori"},"swwiki":{"site":"swwiki","title":"Alibori","badges":[],"url":"https://sw.wikipedia.org/wiki/Alibori"},"tgwiki":{"site":"tgwiki","title":"\u0412\u0438\u043b\u043e\u044f\u0442\u0438 \u0410\u043b\u0438\u0431\u043e\u0440\u0438","badges":[],"url":"https://tg.wikipedia.org/wiki/%D0%92%D0%B8%D0%BB%D0%BE%D1%8F%D1%82%D0%B8_%D0%90%D0%BB%D0%B8%D0%B1%D0%BE%D1%80%D0%B8"},"trwiki":{"site":"trwiki","title":"Alibori Departman\u0131","badges":[],"url":"https://tr.wikipedia.org/wiki/Alibori_Departman%C4%B1"},"ukwiki":{"site":"ukwiki","title":"\u0410\u043b\u0456\u0431\u043e\u0440\u0456 (\u0434\u0435\u043f\u0430\u0440\u0442\u0430\u043c\u0435\u043d\u0442)","badges":[],"url":"https://uk.wikipedia.org/wiki/%D0%90%D0%BB%D1%96%D0%B1%D0%BE%D1%80%D1%96_(%D0%B4%D0%B5%D0%BF%D0%B0%D1%80%D1%82%D0%B0%D0%BC%D0%B5%D0%BD%D1%82)"},"urwiki":{"site":"urwiki","title":"\u0627\u0644\u06cc\u0628\u0648\u0631\u06cc \u0645\u062d\u06a9\u0645\u06c1","badges":[],"url":"https://ur.wikipedia.org/wiki/%D8%A7%D9%84%DB%8C%D8%A8%D9%88%D8%B1%DB%8C_%D9%85%D8%AD%DA%A9%D9%85%DB%81"},"viwiki":{"site":"viwiki","title":"Alibori (t\u1ec9nh)","badges":[],"url":"https://vi.wikipedia.org/wiki/Alibori_(t%E1%BB%89nh)"},"wuuwiki":{"site":"wuuwiki","title":"\u963f\u9ece\u535a\u91cc\u7701","badges":[],"url":"https://wuu.wikipedia.org/wiki/%E9%98%BF%E9%BB%8E%E5%8D%9A%E9%87%8C%E7%9C%81"},"yowiki":{"site":"yowiki","title":"Ap\u00e1 Alibori","badges":[],"url":"https://yo.wikipedia.org/wiki/Ap%C3%A1_Alibori"},"zh_min_nanwiki":{"site":"zh_min_nanwiki","title":"Alibori Ko\u0101n","badges":[],"url":"https://zh-min-nan.wikipedia.org/wiki/Alibori_Ko%C4%81n"},"zhwiki":{"site":"zhwiki","title":"\u963f\u9ece\u535a\u91cc\u7701","badges":[],"url":"https://zh.wikipedia.org/wiki/%E9%98%BF%E9%BB%8E%E5%8D%9A%E9%87%8C%E7%9C%81"}}}}}