{  "http://dbpedia.org/resource/Tour_of_Duty_(TV_series)" : { "http://www.w3.org/1999/02/22-rdf-syntax-ns#type" : [ { "type" : "uri", "value" : "http://dbpedia.org/class/yago/ChangeOfState100199130" } ,      { "type" : "uri", "value" : "http://dbpedia.org/class/yago/Act100030358" } ,      { "type" : "uri", "value" : "http://dbpedia.org/class/yago/Show100520257" } ,      { "type" : "uri", "value" : "http://dbpedia.org/class/yago/Beginning100235435" } ,      { "type" : "uri", "value" : "http://dbpedia.org/class/yago/Activity100407535" } ,      { "type" : "uri", "value" : "http://dbpedia.org/class/yago/Entertainment100429048" } ,      { "type" : "uri", "value" : "http://dbpedia.org/class/yago/WikicatCBSNetworkShows" } ,      { "type" : "uri", "value" : "http://dbpedia.org/class/yago/Wikicat1990AmericanTelevisionSeriesEndings" } ,      { "type" : "uri", "value" : "http://dbpedia.org/class/yago/Introduction100238022" } ,      { "type" : "uri", "value" : "http://dbpedia.org/class/yago/Ending106308765" } ,      { "type" : "uri", "value" : "http://dbpedia.org/class/yago/Morpheme106306233" } ,      { "type" : "uri", "value" : "http://dbpedia.org/class/yago/Change100191142" } ,      { "type" : "uri", "value" : "http://dbpedia.org/class/yago/Action100037396" } ,      { "type" : "uri", "value" : "http://www.w3.org/2002/07/owl#Thing" } ,      { "type" : "uri", "value" : "http://dbpedia.org/class/yago/Abstraction100002137" } ,      { "type" : "uri", "value" : "http://dbpedia.org/class/yago/Event100029378" } ,      { "type" : "uri", "value" : "http://dbpedia.org/ontology/Work" } ,      { "type" : "uri", "value" : "http://dbpedia.org/class/yago/PsychologicalFeature100023100" } ,      { "type" : "uri", "value" : "http://www.wikidata.org/entity/Q386724" } ,      { "type" : "uri", "value" : "http://dbpedia.org/class/yago/Wikicat1987TelevisionSeriesDebuts" } ,      { "type" : "uri", "value" : "http://www.wikidata.org/entity/Q15416" } ,      { "type" : "uri", "value" : "http://dbpedia.org/class/yago/Part113809207" } ,      { "type" : "uri", "value" : "http://dbpedia.org/class/yago/YagoPermanentlyLocatedEntity" } ,      { "type" : "uri", "value" : "http://dbpedia.org/class/yago/Diversion100426928" } ,      { "type" : "uri", "value" : "http://schema.org/CreativeWork" } ,      { "type" : "uri", "value" : "http://dbpedia.org/class/yago/LanguageUnit106284225" } ,      { "type" : "uri", "value" : "http://dbpedia.org/class/yago/Relation100031921" } ,      { "type" : "uri", "value" : "http://dbpedia.org/class/yago/Wikicat1987AmericanTelevisionSeriesDebuts" } ,      { "type" : "uri", "value" : "http://dbpedia.org/ontology/TelevisionShow" } ] ,    "http://www.w3.org/2000/01/rdf-schema#label" : [ { "type" : "literal", "value" : "L'Enfer du devoir (s\u00E9rie t\u00E9l\u00E9vis\u00E9e)" , "lang" : "fr" } ,      { "type" : "literal", "value" : "Tour of Duty (TV series)" , "lang" : "en" } ,      { "type" : "literal", "value" : "Tour of Duty" , "lang" : "es" } ,      { "type" : "literal", "value" : "NAM \u2013 Dienst in Vietnam" , "lang" : "de" } ,      { "type" : "literal", "value" : "\u010Ceta v akci" , "lang" : "cs" } ,      { "type" : "literal", "value" : "Vietnam addio" , "lang" : "it" } ,      { "type" : "literal", "value" : "\u0421\u043B\u0443\u0436\u0435\u0431\u043D\u0430\u044F \u043A\u043E\u043C\u0430\u043D\u0434\u0438\u0440\u043E\u0432\u043A\u0430 (\u0442\u0435\u043B\u0435\u0441\u0435\u0440\u0438\u0430\u043B)" , "lang" : "ru" } ,      { "type" : "literal", "value" : "Pluton B i Vietnam" , "lang" : "sv" } ,      { "type" : "literal", "value" : "Combate no Vietn\u00E3 (s\u00E9rie de televis\u00E3o)" , "lang" : "pt" } ,      { "type" : "literal", "value" : "\uBA38\uB098\uBA3C \uC815\uAE00" , "lang" : "ko" } ,      { "type" : "literal", "value" : "Tour of Duty" , "lang" : "nl" } ] ,    "http://www.w3.org/2000/01/rdf-schema#comment" : [ { "type" : "literal", "value" : "Pluton B i Vietnam (orig. titel \"Tour of Duty\") var en amerikansk TV-serie som spelades in 1987-1990 och s\u00E4ndes bland annat p\u00E5 Kanal 5 i Sverige under titeln \"Pluton B i Vietnam\". Serien handlar om en grupp soldater under Vietnamkriget. Serien, som blev tre s\u00E4songer l\u00E5ng, tar upp problem i det krigsh\u00E4rjade Vietnam. Allt fr\u00E5n rasism mellan amerikanska soldater och drogproblem i Vietnam till veteranernas kamp. Namnet \"Tour of duty\" kommer fr\u00E5n det amerikanska uttrycket. En \"tour\" var ett \u00E5r l\u00E5ng och var den tid man normalt tj\u00E4nstgjorde i Vietnam." , "lang" : "sv" } ,      { "type" : "literal", "value" : "\u300A\uBA38\uB098\uBA3C \uC815\uAE00\u300B\uC740 \uBBF8\uAD6D CBS\uC758 TV \uC2DC\uB9AC\uC988\uBB3C\uC774\uB2E4. \uC2A4\uD2F0\uBE10 \uCE74\uD504\uB9AC\uC758 \uC8FC\uC5F0\uC73C\uB85C CBSf\uB97C \uD1B5\uD574 1987\uB144 9\uC6D4 24\uC77C\uBD80\uD130 1990\uB144 4\uC6D4 28\uC77C\uAE4C\uC9C0 \uBC29\uC601\uB418\uC5C8\uB2E4. \uBCA0\uD2B8\uB0A8 \uC804\uC7C1\uC744 \uBC30\uACBD\uC73C\uB85C \uD55C \uC804\uC7C1 \uB4DC\uB77C\uB9C8\uB85C \uB9C8\uC774\uB7F0 \uACE8\uB4DC\uBA3C\uC740 \uC7A5\uAD50\uC758 \uAD00\uC810\uC5D0\uC11C, \uC81C\uC774\uD06C \uC564\uB354\uC2A8\uC740 \uC0AC\uBCD1\uC758 \uAD00\uC810\uC5D0\uC11C \uAC01\uAC01 \uC774 \uB4DC\uB77C\uB9C8\uB97C \uBC14\uB77C\uBCF4\uACE0 \uC788\uB2E4. \uB300\uD55C\uBBFC\uAD6D\uC5D0\uC11C\uB294 MBC\uC5D0\uC11C \uC218\uC785\uD558\uC5EC 1988\uB144 11\uC6D4 30\uC77C\uBD80\uD130 1991\uB144 4\uC6D4 13\uC77C\uAE4C\uC9C0 \uBC29\uC601\uB418\uC5C8\uB2E4." , "lang" : "ko" } ,      { "type" : "literal", "value" : "Tour of Duty is an American military drama television series based on events in the Vietnam War, broadcast on CBS. The series ran for three seasons, from September 24, 1987, to April 28, 1990, for a total of 58 one-hour episodes. The show was created by Steve Duncan and L. Travis Clark and produced by Zev Braun. The series won an Emmy Award in 1988 for Outstanding Sound Mixing for a Drama Series, and it was nominated again in 1989 and 1990." , "lang" : "en" } ,      { "type" : "literal", "value" : "Vietnam addio (Tour of Duty) \u00E8 una serie televisiva statunitense in 58 episodi trasmessi per la prima volta nel corso di 3 stagioni dal 1987 al 1990. \u00C8 una serie di guerra incentrata sulle vicende di un plotone di fanteria americano durante la guerra del Vietnam. \u00C8 stata la prima serie televisiva a rappresentare militari statunitensi in combattimento in Vietnam; fu prodotta sulla scia del celebre film di Oliver Stone, Platoon. La serie ha vinto un premio Emmy nel 1988 nella categoria Outstanding Sound Mixing for a Drama Series ed ottenne due nomination nel 1989 e 1990. Vietnam addio si rivel\u00F2 una produzione innovativa in quanto affronta nel corso degli episodi, oltre al tema drammatico come la guerra, anche temi quali la politica, la fede, il razzismo, i suicidi, il fragging, il terrorismo" , "lang" : "it" } ,      { "type" : "literal", "value" : "L'Enfer du devoir ou Commando Vi\u00EAt Nam (Tour of Duty) est une s\u00E9rie t\u00E9l\u00E9vis\u00E9e am\u00E9ricaine en 58 \u00E9pisodes de 50 minutes, cr\u00E9\u00E9e par et et diffus\u00E9e entre le 24 septembre 1987 et le 28 avril 1990 sur le r\u00E9seau CBS. En France, la s\u00E9rie a \u00E9t\u00E9 diffus\u00E9e entre le 16 octobre 1988 et le 9 juin 1991 sur La Cinq et sur RTL T\u00E9l\u00E9vision, puis en partie car arr\u00EAt\u00E9e faute d'audience en 1995 sur TF1, diffus\u00E9e en 2003 sur S\u00E9rie club et enfin rediffus\u00E9e sur Direct 8 en 2008. Au Qu\u00E9bec, elle a \u00E9t\u00E9 diffus\u00E9e sur Historia." , "lang" : "fr" } ,      { "type" : "literal", "value" : "Tour of Duty (Combate no Vietn\u00E3 no Brasil) \u00E9 uma s\u00E9rie de televis\u00E3o americana que foi ao ar entre 1987 e 1990, com base em eventos da Guerra do Vietn\u00E3. A s\u00E9rie teve tr\u00EAs temporadas, come\u00E7ando em setembro de 1987 e terminando em abril de 1990, com um total de 58 epis\u00F3dios. A s\u00E9rie foi criada por Steve Duncan e L. Travis Clark e produzido por Zev Braun." , "lang" : "pt" } ,      { "type" : "literal", "value" : "Tour of Duty es una serie de televisi\u00F3n estadounidense de g\u00E9nero dram\u00E1tico, que originalmente estuvo al aire de 1987 hasta 1990. El programa trata de un pelot\u00F3n estadounidense en servicio activo durante la Guerra de Vietnam. Fue una de varias producciones relacionadas con la guerra de Vietnam que siguieron a la afamada pel\u00EDcula Platoon, de Oliver Stone." , "lang" : "es" } ,      { "type" : "literal", "value" : "NAM \u2013 Dienst in Vietnam (Originaltitel: Tour of Duty) ist eine US-amerikanische Fernsehserie \u00FCber ein Platoon im Vietnamkrieg. Die Serie hat 58 Episoden und wurde in drei Staffeln von 1987 bis 1990 produziert." , "lang" : "de" } ,      { "type" : "literal", "value" : "\u010Ceta v akci (v anglick\u00E9m origin\u00E1le Tour of Duty) je americk\u00FD v\u00E1le\u010Dn\u00FD televizn\u00ED seri\u00E1l z vietnamsk\u00E9 v\u00E1lky, nat\u00E1\u010Del se v letech 1987\u20131990. M\u00E1 celkem 3 s\u00E9rie a 58 epizod." , "lang" : "cs" } ,      { "type" : "literal", "value" : "Tour of Duty was een Amerikaanse dramaserie over de Vietnamoorlog die op de Amerikaanse televisie werd uitgezonden van 1987 tot 1990.De titelsong was vanaf de tweede aflevering Paint It Black van The Rolling Stones. De serie bestaat uit drie seizoenen. In het eerste seizoen, beginnend in het tweede deel van 1967, behoort het peloton tot de 196th Light Infantry Brigade met als basiskamp Chu Lai. Het peloton is in Chu Lai slechts enkele malen terug te vinden en is grotendeels te zien op Firebase Ladybird of in de jungle." , "lang" : "nl" } ,      { "type" : "literal", "value" : "\u00AB\u0421\u043B\u0443\u0436\u0435\u0431\u043D\u0430\u044F \u043A\u043E\u043C\u0430\u043D\u0434\u0438\u0440\u043E\u0432\u043A\u0430\u00BB (\u0438\u0437\u0432\u0435\u0441\u0442\u0435\u043D \u0442\u0430\u043A\u0436\u0435 \u043F\u043E\u0434 \u043D\u0430\u0437\u0432\u0430\u043D\u0438\u0435\u043C \u00AB\u0421\u0440\u043E\u043A \u0441\u043B\u0443\u0436\u0431\u044B\u00BB) \u2014 \u0430\u043C\u0435\u0440\u0438\u043A\u0430\u043D\u0441\u043A\u0430\u044F \u0442\u0435\u043B\u0435\u0434\u0440\u0430\u043C\u0430, \u0432\u044B\u0448\u0435\u0434\u0448\u0430\u044F \u043D\u0430 \u043A\u0430\u043D\u0430\u043B\u0435 CBS \u0441 \u0441\u0435\u043D\u0442\u044F\u0431\u0440\u044F 1987 \u043F\u043E \u0430\u043F\u0440\u0435\u043B\u044C 1990 \u0433\u043E\u0434\u0430. \u0421\u0435\u0440\u0438\u0430\u043B \u043F\u043E\u043A\u0430\u0437\u044B\u0432\u0430\u043B \u0441\u043B\u0443\u0436\u0431\u0443 \u0432\u0437\u0432\u043E\u0434\u0430 \u043F\u0435\u0445\u043E\u0442\u044B \u0432\u043E \u0412\u044C\u0435\u0442\u043D\u0430\u043C\u0441\u043A\u043E\u0439 \u0432\u043E\u0439\u043D\u0435. \u041E\u043D \u0441\u0442\u0430\u043B \u043F\u0435\u0440\u0432\u044B\u043C \u043F\u043E\u0441\u0442\u043E\u044F\u043D\u043D\u044B\u043C \u0442\u0435\u043B\u0435\u0441\u0435\u0440\u0438\u0430\u043B\u043E\u043C \u043E \u0431\u0438\u0442\u0432\u0435 \u0432\u043E \u0412\u044C\u0435\u0442\u043D\u0430\u043C\u0435 \u0438 \u0431\u044B\u043B \u043E\u0434\u043D\u0438\u043C \u0438\u0437 \u043D\u0435\u0441\u043A\u043E\u043B\u044C\u043A\u0438\u0445 \u0441\u0435\u0440\u0438\u0430\u043B\u043E\u0432 \u0430\u043D\u0430\u043B\u043E\u0433\u0438\u0447\u043D\u043E\u0439 \u0442\u0435\u043C\u0430\u0442\u0438\u043A\u0438, \u0432\u044B\u0448\u0435\u0434\u0448\u0438\u0439 \u0432\u0441\u043B\u0435\u0434 \u0437\u0430 \u00AB\u0412\u0437\u0432\u043E\u0434\u043E\u043C\u00BB \u041E\u043B\u0438\u0432\u0435\u0440\u0430 \u0421\u0442\u043E\u0443\u043D\u0430. \u0421\u0435\u0440\u0438\u0430\u043B \u0431\u044B\u043B \u0441\u043E\u0437\u0434\u0430\u043D \u0438 \u0438 \u0441\u043F\u0440\u043E\u0434\u044E\u0441\u0438\u0440\u043E\u0432\u0430\u043D . \u0421\u0435\u0440\u0438\u0430\u043B \u0432\u044B\u0445\u043E\u0434\u0438\u043B \u0442\u0440\u0435\u043C\u044F \u0441\u0435\u0437\u043E\u043D\u0430\u043C\u0438 \u0432 \u0432\u0438\u0434\u0435 58 \u043E\u0434\u043D\u043E\u0447\u0430\u0441\u043E\u0432\u044B\u0445 \u044D\u043F\u0438\u0437\u043E\u0434\u043E\u0432." , "lang" : "ru" } ] ,    "http://xmlns.com/foaf/0.1/homepage" : [ { "type" : "uri", "value" : "https://web.archive.org/web/20120225032057/http:/www.totalfanhub.com/tour-of-duty/" } ] ,    "http://xmlns.com/foaf/0.1/depiction" : [ { "type" : "uri", "value" : "http://commons.wikimedia.org/wiki/Special:FilePath/Tour_of_duty_tv_series.jpg" } ] ,    "http://purl.org/dc/terms/subject" : [ { "type" : "uri", "value" : "http://dbpedia.org/resource/Category:American_military_television_series" } ,      { "type" : "uri", "value" : "http://dbpedia.org/resource/Category:1990_American_television_series_endings" } ,      { "type" : "uri", "value" : "http://dbpedia.org/resource/Category:Television_series_by_New_World_Television" } ,      { "type" : "uri", "value" : "http://dbpedia.org/resource/Category:Television_series_by_Sony_Pictures_Television" } ,      { "type" : "uri", "value" : "http://dbpedia.org/resource/Category:Television_series_set_in_1967" } ,      { "type" : "uri", "value" : "http://dbpedia.org/resource/Category:CBS_original_programming" } ,      { "type" : "uri", "value" : "http://dbpedia.org/resource/Category:Television_series_set_in_1969" } ,      { "type" : "uri", "value" : "http://dbpedia.org/resource/Category:English-language_television_shows" } ,      { "type" : "uri", "value" : "http://dbpedia.org/resource/Category:Television_series_based_on_actual_events" } ,      { "type" : "uri", "value" : "http://dbpedia.org/resource/Category:1987_American_television_series_debuts" } ,      { "type" : "uri", "value" : "http://dbpedia.org/resource/Category:Television_series_about_Vietnam_War" } ,      { "type" : "uri", "value" : "http://dbpedia.org/resource/Category:Television_series_set_in_1968" } ] ,    "http://dbpedia.org/ontology/abstract" : [ { "type" : "literal", "value" : "\u300A\uBA38\uB098\uBA3C \uC815\uAE00\u300B\uC740 \uBBF8\uAD6D CBS\uC758 TV \uC2DC\uB9AC\uC988\uBB3C\uC774\uB2E4. \uC2A4\uD2F0\uBE10 \uCE74\uD504\uB9AC\uC758 \uC8FC\uC5F0\uC73C\uB85C CBSf\uB97C \uD1B5\uD574 1987\uB144 9\uC6D4 24\uC77C\uBD80\uD130 1990\uB144 4\uC6D4 28\uC77C\uAE4C\uC9C0 \uBC29\uC601\uB418\uC5C8\uB2E4. \uBCA0\uD2B8\uB0A8 \uC804\uC7C1\uC744 \uBC30\uACBD\uC73C\uB85C \uD55C \uC804\uC7C1 \uB4DC\uB77C\uB9C8\uB85C \uB9C8\uC774\uB7F0 \uACE8\uB4DC\uBA3C\uC740 \uC7A5\uAD50\uC758 \uAD00\uC810\uC5D0\uC11C, \uC81C\uC774\uD06C \uC564\uB354\uC2A8\uC740 \uC0AC\uBCD1\uC758 \uAD00\uC810\uC5D0\uC11C \uAC01\uAC01 \uC774 \uB4DC\uB77C\uB9C8\uB97C \uBC14\uB77C\uBCF4\uACE0 \uC788\uB2E4. \uB300\uD55C\uBBFC\uAD6D\uC5D0\uC11C\uB294 MBC\uC5D0\uC11C \uC218\uC785\uD558\uC5EC 1988\uB144 11\uC6D4 30\uC77C\uBD80\uD130 1991\uB144 4\uC6D4 13\uC77C\uAE4C\uC9C0 \uBC29\uC601\uB418\uC5C8\uB2E4." , "lang" : "ko" } ,      { "type" : "literal", "value" : "\u00AB\u0421\u043B\u0443\u0436\u0435\u0431\u043D\u0430\u044F \u043A\u043E\u043C\u0430\u043D\u0434\u0438\u0440\u043E\u0432\u043A\u0430\u00BB (\u0438\u0437\u0432\u0435\u0441\u0442\u0435\u043D \u0442\u0430\u043A\u0436\u0435 \u043F\u043E\u0434 \u043D\u0430\u0437\u0432\u0430\u043D\u0438\u0435\u043C \u00AB\u0421\u0440\u043E\u043A \u0441\u043B\u0443\u0436\u0431\u044B\u00BB) \u2014 \u0430\u043C\u0435\u0440\u0438\u043A\u0430\u043D\u0441\u043A\u0430\u044F \u0442\u0435\u043B\u0435\u0434\u0440\u0430\u043C\u0430, \u0432\u044B\u0448\u0435\u0434\u0448\u0430\u044F \u043D\u0430 \u043A\u0430\u043D\u0430\u043B\u0435 CBS \u0441 \u0441\u0435\u043D\u0442\u044F\u0431\u0440\u044F 1987 \u043F\u043E \u0430\u043F\u0440\u0435\u043B\u044C 1990 \u0433\u043E\u0434\u0430. \u0421\u0435\u0440\u0438\u0430\u043B \u043F\u043E\u043A\u0430\u0437\u044B\u0432\u0430\u043B \u0441\u043B\u0443\u0436\u0431\u0443 \u0432\u0437\u0432\u043E\u0434\u0430 \u043F\u0435\u0445\u043E\u0442\u044B \u0432\u043E \u0412\u044C\u0435\u0442\u043D\u0430\u043C\u0441\u043A\u043E\u0439 \u0432\u043E\u0439\u043D\u0435. \u041E\u043D \u0441\u0442\u0430\u043B \u043F\u0435\u0440\u0432\u044B\u043C \u043F\u043E\u0441\u0442\u043E\u044F\u043D\u043D\u044B\u043C \u0442\u0435\u043B\u0435\u0441\u0435\u0440\u0438\u0430\u043B\u043E\u043C \u043E \u0431\u0438\u0442\u0432\u0435 \u0432\u043E \u0412\u044C\u0435\u0442\u043D\u0430\u043C\u0435 \u0438 \u0431\u044B\u043B \u043E\u0434\u043D\u0438\u043C \u0438\u0437 \u043D\u0435\u0441\u043A\u043E\u043B\u044C\u043A\u0438\u0445 \u0441\u0435\u0440\u0438\u0430\u043B\u043E\u0432 \u0430\u043D\u0430\u043B\u043E\u0433\u0438\u0447\u043D\u043E\u0439 \u0442\u0435\u043C\u0430\u0442\u0438\u043A\u0438, \u0432\u044B\u0448\u0435\u0434\u0448\u0438\u0439 \u0432\u0441\u043B\u0435\u0434 \u0437\u0430 \u00AB\u0412\u0437\u0432\u043E\u0434\u043E\u043C\u00BB \u041E\u043B\u0438\u0432\u0435\u0440\u0430 \u0421\u0442\u043E\u0443\u043D\u0430. \u0421\u0435\u0440\u0438\u0430\u043B \u0431\u044B\u043B \u0441\u043E\u0437\u0434\u0430\u043D \u0438 \u0438 \u0441\u043F\u0440\u043E\u0434\u044E\u0441\u0438\u0440\u043E\u0432\u0430\u043D . \u0421\u0435\u0440\u0438\u0430\u043B \u0432\u044B\u0445\u043E\u0434\u0438\u043B \u0442\u0440\u0435\u043C\u044F \u0441\u0435\u0437\u043E\u043D\u0430\u043C\u0438 \u0432 \u0432\u0438\u0434\u0435 58 \u043E\u0434\u043D\u043E\u0447\u0430\u0441\u043E\u0432\u044B\u0445 \u044D\u043F\u0438\u0437\u043E\u0434\u043E\u0432." , "lang" : "ru" } ,      { "type" : "literal", "value" : "Tour of Duty (Combate no Vietn\u00E3 no Brasil) \u00E9 uma s\u00E9rie de televis\u00E3o americana que foi ao ar entre 1987 e 1990, com base em eventos da Guerra do Vietn\u00E3. A s\u00E9rie teve tr\u00EAs temporadas, come\u00E7ando em setembro de 1987 e terminando em abril de 1990, com um total de 58 epis\u00F3dios. A s\u00E9rie foi criada por Steve Duncan e L. Travis Clark e produzido por Zev Braun. A s\u00E9rie acompanha um pelot\u00E3o de infantaria durante a Guerra do Vietn\u00E3. Foi a primeira s\u00E9rie de televis\u00E3o regularmente mostrando soldados Norte-americanos em combate no Vietn\u00E3 e foi uma das v\u00E1rias s\u00E9ries de TV com o mesmo tema a ser produzido na sequ\u00EAncia do filme Platoon, de Oliver Stone. A s\u00E9rie ganhou um Emmy, em 1988, por sua mixagem de Som para uma S\u00E9rie de Drama, tendo sido indicada novamente em 1989 e 1990." , "lang" : "pt" } ,      { "type" : "literal", "value" : "Tour of Duty was een Amerikaanse dramaserie over de Vietnamoorlog die op de Amerikaanse televisie werd uitgezonden van 1987 tot 1990.De titelsong was vanaf de tweede aflevering Paint It Black van The Rolling Stones. De serie bestaat uit drie seizoenen. In het eerste seizoen, beginnend in het tweede deel van 1967, behoort het peloton tot de 196th Light Infantry Brigade met als basiskamp Chu Lai. Het peloton is in Chu Lai slechts enkele malen terug te vinden en is grotendeels te zien op Firebase Ladybird of in de jungle. Het tweede seizoen start in januari 1968 waar we het peloton nu zien als onderdeel van MACV (Military Assistence Command Vietnam), gestationeerd te , Saigon. Hier voeren ze verschillende taken uit welke gaan van bewakingsopdrachten tot de typische Search and Destroy missions.Ook spelen in dit seizoen meerdere vrouwelijke personages mee om zo meer vrouwelijke kijkers te trekken.Dit betekende volgens de makers het einde van de serie, al werd het ook veroorzaakt door de programmering tegenover andere populaire series op andere zenders. Het derde seizoen brengt het peloton naar Camp Barnett, een Special Forces Camp waar ze wegens een tekort aan manschappen ter ondersteuning worden toegevoegd aan de Special Forces Group. Uiteindelijk worden de hoofdpersonages opgenomen in de Studies and Observations Group (SOG) genaamd als Team-Viking dat zowel opereert in Vietnam als Cambodja.Naar het einde van seizoen drie worden de SOG-operaties stopgezet en wordt het peloton opnieuw gevormd. De serie was vernieuwend omdat zij in tegenstelling tot veel andere films en series ook regelmatig ernstige verwondingen en doden toonde. Ook kwamen sociale problemen als racisme, zelfmoord, terrorisme, oorlogsmisdaden en drugsgebruik aan bod. De serie werd tussen 1990 en 1993 in Nederland uitgezonden door het publieke Veronica op Nederland 2 en was enorm populair met hoge kijkcijfers. Er zijn diverse CD's uitgebracht met hits uit de serie. De titelsong Paint It Black van The Rolling Stones werd vanaf eind april 1990 opnieuw een grote hit en werd veel gedraaid op de TROS donderdag en de volle vrijdag van Veronica op de nationale publieke popzender Radio 3. De plaat bereikte de nummer 1-positie in zowel de Nederlandse Top 40 als de Nationale Top 100. In Belgi\u00EB werd de serie destijds op televisie uitgezonden op het eerste net door de Vlaamse BRT." , "lang" : "nl" } ,      { "type" : "literal", "value" : "Vietnam addio (Tour of Duty) \u00E8 una serie televisiva statunitense in 58 episodi trasmessi per la prima volta nel corso di 3 stagioni dal 1987 al 1990. \u00C8 una serie di guerra incentrata sulle vicende di un plotone di fanteria americano durante la guerra del Vietnam. \u00C8 stata la prima serie televisiva a rappresentare militari statunitensi in combattimento in Vietnam; fu prodotta sulla scia del celebre film di Oliver Stone, Platoon. La serie ha vinto un premio Emmy nel 1988 nella categoria Outstanding Sound Mixing for a Drama Series ed ottenne due nomination nel 1989 e 1990. Vietnam addio si rivel\u00F2 una produzione innovativa in quanto affronta nel corso degli episodi, oltre al tema drammatico come la guerra, anche temi quali la politica, la fede, il razzismo, i suicidi, il fragging, il terrorismo, le conseguenze del conflitto sui civili, l'abuso di droghe." , "lang" : "it" } ,      { "type" : "literal", "value" : "NAM \u2013 Dienst in Vietnam (Originaltitel: Tour of Duty) ist eine US-amerikanische Fernsehserie \u00FCber ein Platoon im Vietnamkrieg. Die Serie hat 58 Episoden und wurde in drei Staffeln von 1987 bis 1990 produziert." , "lang" : "de" } ,      { "type" : "literal", "value" : "\u010Ceta v akci (v anglick\u00E9m origin\u00E1le Tour of Duty) je americk\u00FD v\u00E1le\u010Dn\u00FD televizn\u00ED seri\u00E1l z vietnamsk\u00E9 v\u00E1lky, nat\u00E1\u010Del se v letech 1987\u20131990. M\u00E1 celkem 3 s\u00E9rie a 58 epizod." , "lang" : "cs" } ,      { "type" : "literal", "value" : "Tour of Duty is an American military drama television series based on events in the Vietnam War, broadcast on CBS. The series ran for three seasons, from September 24, 1987, to April 28, 1990, for a total of 58 one-hour episodes. The show was created by Steve Duncan and L. Travis Clark and produced by Zev Braun. The show follows an American infantry platoon on a tour of duty during the Vietnam War. It was the first television series to regularly show Americans in combat in South Vietnam and was one of several similarly themed series to be produced in the wake of the acclaimed Oliver Stone film Platoon (1986). The series won an Emmy Award in 1988 for Outstanding Sound Mixing for a Drama Series, and it was nominated again in 1989 and 1990." , "lang" : "en" } ,      { "type" : "literal", "value" : "L'Enfer du devoir ou Commando Vi\u00EAt Nam (Tour of Duty) est une s\u00E9rie t\u00E9l\u00E9vis\u00E9e am\u00E9ricaine en 58 \u00E9pisodes de 50 minutes, cr\u00E9\u00E9e par et et diffus\u00E9e entre le 24 septembre 1987 et le 28 avril 1990 sur le r\u00E9seau CBS. En France, la s\u00E9rie a \u00E9t\u00E9 diffus\u00E9e entre le 16 octobre 1988 et le 9 juin 1991 sur La Cinq et sur RTL T\u00E9l\u00E9vision, puis en partie car arr\u00EAt\u00E9e faute d'audience en 1995 sur TF1, diffus\u00E9e en 2003 sur S\u00E9rie club et enfin rediffus\u00E9e sur Direct 8 en 2008. Au Qu\u00E9bec, elle a \u00E9t\u00E9 diffus\u00E9e sur Historia." , "lang" : "fr" } ,      { "type" : "literal", "value" : "Tour of Duty es una serie de televisi\u00F3n estadounidense de g\u00E9nero dram\u00E1tico, que originalmente estuvo al aire de 1987 hasta 1990. El programa trata de un pelot\u00F3n estadounidense en servicio activo durante la Guerra de Vietnam. Fue una de varias producciones relacionadas con la guerra de Vietnam que siguieron a la afamada pel\u00EDcula Platoon, de Oliver Stone. La serie tambi\u00E9n fue conocida como Misi\u00F3n del deber en Latinoam\u00E9rica, Misi\u00F3n Vietnam en El Salvador, NAM en Per\u00FA, Pelot\u00F3n del deber en Venezuela, NAM, Primer Pelot\u00F3n en Argentina, Combate en Vietnam en Uruguay, y como Camino al Infierno en Espa\u00F1a. La serie tuvo tres temporadas, con un total de 58 episodios, de una hora cada uno. La canci\u00F3n del programa (y que contribuy\u00F3 mucho a la popularidad del show) era \"Paint It, Black\", de los Rolling Stones, aunque tambi\u00E9n hab\u00EDa canciones de Creedence Clearwater Revival, Jimi Hendrix, y Jefferson Airplane. El programa gan\u00F3 un Emmy en 1988 por su sobresaliente mezcla de audio para una serie dram\u00E1tica, y fue nominada otra vez en 1989 y 1990.\u200B Las versiones de VHS y DVD tuvieron que usar m\u00FAsica de bandas menos conocidas por razones de derechos de autor." , "lang" : "es" } ,      { "type" : "literal", "value" : "Pluton B i Vietnam (orig. titel \"Tour of Duty\") var en amerikansk TV-serie som spelades in 1987-1990 och s\u00E4ndes bland annat p\u00E5 Kanal 5 i Sverige under titeln \"Pluton B i Vietnam\". Serien handlar om en grupp soldater under Vietnamkriget. Serien, som blev tre s\u00E4songer l\u00E5ng, tar upp problem i det krigsh\u00E4rjade Vietnam. Allt fr\u00E5n rasism mellan amerikanska soldater och drogproblem i Vietnam till veteranernas kamp. Namnet \"Tour of duty\" kommer fr\u00E5n det amerikanska uttrycket. En \"tour\" var ett \u00E5r l\u00E5ng och var den tid man normalt tj\u00E4nstgjorde i Vietnam. Serien anv\u00E4nde sig av m\u00E5nga g\u00E4stsk\u00E5despelare som till exempel Ving Rhames och Michael Madsen." , "lang" : "sv" } ] ,    "http://dbpedia.org/ontology/wikiPageWikiLink" : [ { "type" : "uri", "value" : "http://dbpedia.org/resource/James_Hong" } ,      { "type" : "uri", "value" : "http://dbpedia.org/resource/Eddie_Award" } ,      { "type" : "uri", "value" : "http://dbpedia.org/resource/Columbia_Pictures_Television" } ,      { "type" : "uri", "value" : "http://dbpedia.org/resource/Suicide" } ,      { "type" : "uri", "value" : "http://dbpedia.org/resource/Sergeant_first_class" } ,      { "type" : "uri", "value" : "http://dbpedia.org/resource/Columbia_TriStar_Television" } ,      { "type" : "uri", "value" : "http://dbpedia.org/resource/The_Rolling_Stones" } ,      { "type" : "uri", "value" : "http://dbpedia.org/resource/Tour_of_duty" } ,      { "type" : "uri", "value" : "http://dbpedia.org/resource/L._Travis_Clark" } ,      { "type" : "uri", "value" : "http://dbpedia.org/resource/Koch_Media" } ,      { "type" : "uri", "value" : "http://dbpedia.org/resource/Category:CBS_original_programming" } ,      { "type" : "uri", "value" : "http://dbpedia.org/resource/Emmy_Award" } ,      { "type" : "uri", "value" : "http://dbpedia.org/resource/Category:1987_American_television_series_debuts" } ,      { "type" : "uri", "value" : "http://dbpedia.org/resource/Collateral_damage" } ,      { "type" : "uri", "value" : "http://dbpedia.org/resource/1987_in_cinema" } ,      { "type" : "uri", "value" : "http://dbpedia.org/resource/Category:Television_series_set_in_1968" } ,      { "type" : "uri", "value" : "http://dbpedia.org/resource/Military_drama" } ,      { "type" : "uri", "value" : "http://dbpedia.org/resource/David_Alan_Grier" } ,      { "type" : "uri", "value" : "http://dbpedia.org/resource/Alan_Scarfe" } ,      { "type" : "uri", "value" : "http://dbpedia.org/resource/Tour_of_Duty_(season_2)" } ,      { "type" : "uri", "value" : "http://dbpedia.org/resource/Light_infantry" } ,      { "type" : "uri", "value" : "http://dbpedia.org/resource/Vietnam_Magazine" } ,      { "type" : "uri", "value" : "http://dbpedia.org/resource/Have_You_Ever_Seen_the_Rain%3F" } ,      { "type" : "uri", "value" : "http://dbpedia.org/resource/Olivia_d'Abo" } ,      { "type" : "uri", "value" : "http://dbpedia.org/resource/Greg_Germann" } ,      { "type" : "uri", "value" : "http://dbpedia.org/resource/Category:Television_series_set_in_1969" } ,      { "type" : "uri", "value" : "http://dbpedia.org/resource/Sony_Pictures" } ,      { "type" : "uri", "value" : "http://dbpedia.org/resource/Dan_Gauthier" } ,      { "type" : "uri", "value" : "http://dbpedia.org/resource/William_Sadler_(actor)" } ,      { "type" : "uri", "value" : "http://dbpedia.org/resource/Teamwork" } ,      { "type" : "uri", "value" : "http://dbpedia.org/resource/ARIA_Charts" } ,      { "type" : "uri", "value" : "http://dbpedia.org/resource/M*A*S*H_(TV_series)" } ,      { "type" : "uri", "value" : "http://dbpedia.org/resource/Stan_Foster" } ,      { "type" : "uri", "value" : "http://dbpedia.org/resource/VHS" } ,      { "type" : "uri", "value" : "http://dbpedia.org/resource/New_World_Television" } ,      { "type" : "uri", "value" : "http://dbpedia.org/resource/Fragging" } ,      { "type" : "uri", "value" : "http://dbpedia.org/resource/Malcolm-Jamal_Warner" } ,      { "type" : "uri", "value" : "http://dbpedia.org/resource/Michael_Madsen" } ,      { "type" : "uri", "value" : "http://dbpedia.org/resource/Kevin_Conroy" } ,      { "type" : "uri", "value" : "http://dbpedia.org/resource/Category:Television_series_about_Vietnam_War" } ,      { "type" : "uri", "value" : "http://dbpedia.org/resource/Infantry" } ,      { "type" : "uri", "value" : "http://dbpedia.org/resource/Politics" } ,      { "type" : "uri", "value" : "http://dbpedia.org/resource/Zev_Braun" } ,      { "type" : "uri", "value" : "http://dbpedia.org/resource/Schofield_Barracks" } ,      { "type" : "uri", "value" : "http://dbpedia.org/resource/Category:Television_series_by_New_World_Television" } ,      { "type" : "uri", "value" : "http://dbpedia.org/resource/Miguel_A._N\u00FA\u00F1ez_Jr." } ,      { "type" : "uri", "value" : "http://dbpedia.org/resource/Joshua_D._Maurer" } ,      { "type" : "uri", "value" : "http://dbpedia.org/resource/Category:1990_American_television_series_endings" } ,      { "type" : "uri", "value" : "http://dbpedia.org/resource/Sony_Pictures_Television" } ,      { "type" : "uri", "value" : "http://dbpedia.org/resource/Vietnam_War" } ,      { "type" : "uri", "value" : "http://dbpedia.org/resource/Hawaii" } ,      { "type" : "uri", "value" : "http://dbpedia.org/resource/We_Gotta_Get_Out_of_This_Place" } ,      { "type" : "uri", "value" : "http://dbpedia.org/resource/Category:Television_series_by_Sony_Pictures_Television" } ,      { "type" : "uri", "value" : "http://dbpedia.org/resource/Tony_Becker" } ,      { "type" : "uri", "value" : "http://dbpedia.org/resource/Bruce_Gray" } ,      { "type" : "uri", "value" : "http://dbpedia.org/resource/CBS" } ,      { "type" : "uri", "value" : "http://dbpedia.org/resource/Sony_Music" } ,      { "type" : "uri", "value" : "http://dbpedia.org/resource/Category:English-language_television_shows" } ,      { "type" : "uri", "value" : "http://dbpedia.org/resource/Wooly_Bully" } ,      { "type" : "uri", "value" : "http://dbpedia.org/resource/Kim_Delaney" } ,      { "type" : "uri", "value" : "http://dbpedia.org/resource/Copyright" } ,      { "type" : "uri", "value" : "http://dbpedia.org/resource/Stephen_Caffrey_(actor)" } ,      { "type" : "uri", "value" : "http://dbpedia.org/resource/Columbia_Records" } ,      { "type" : "uri", "value" : "http://dbpedia.org/resource/Jefferson_Airplane" } ,      { "type" : "uri", "value" : "http://dbpedia.org/resource/Racism" } ,      { "type" : "uri", "value" : "http://dbpedia.org/resource/Kent_Music_Report" } ,      { "type" : "uri", "value" : "http://dbpedia.org/resource/Ronald_L._Schwary" } ,      { "type" : "uri", "value" : "http://dbpedia.org/resource/Platoon_(film)" } ,      { "type" : "uri", "value" : "http://dbpedia.org/resource/Terrorism" } ,      { "type" : "uri", "value" : "http://dbpedia.org/resource/Television_series" } ,      { "type" : "uri", "value" : "http://dbpedia.org/resource/Paint_It,_Black" } ,      { "type" : "uri", "value" : "http://dbpedia.org/resource/Second_lieutenant" } ,      { "type" : "uri", "value" : "http://dbpedia.org/resource/Category:American_military_television_series" } ,      { "type" : "uri", "value" : "http://dbpedia.org/resource/Drug_abuse" } ,      { "type" : "uri", "value" : "http://dbpedia.org/resource/20th_Century_Fox_Television" } ,      { "type" : "uri", "value" : "http://dbpedia.org/resource/Category:Television_series_set_in_1967" } ,      { "type" : "uri", "value" : "http://dbpedia.org/resource/Staff_sergeant" } ,      { "type" : "uri", "value" : "http://dbpedia.org/resource/Eric_Bruskotter" } ,      { "type" : "uri", "value" : "http://dbpedia.org/resource/Colonel_(United_States)" } ,      { "type" : "uri", "value" : "http://dbpedia.org/resource/Tour_of_Duty_(season_1)" } ,      { "type" : "uri", "value" : "http://dbpedia.org/resource/Jumping_the_shark" } ,      { "type" : "uri", "value" : "http://dbpedia.org/resource/Full_Metal_Jacket" } ,      { "type" : "uri", "value" : "http://dbpedia.org/resource/First_lieutenant" } ,      { "type" : "uri", "value" : "http://dbpedia.org/resource/Richard_Brooks_(actor)" } ,      { "type" : "uri", "value" : "http://dbpedia.org/resource/Sexuality" } ,      { "type" : "uri", "value" : "http://dbpedia.org/resource/Everett_McGill" } ,      { "type" : "uri", "value" : "http://dbpedia.org/resource/DVD" } ,      { "type" : "uri", "value" : "http://dbpedia.org/resource/Covert_operation" } ,      { "type" : "uri", "value" : "http://dbpedia.org/resource/Pamela_Gidley" } ,      { "type" : "uri", "value" : "http://dbpedia.org/resource/Tour_of_Duty_(Season_2)" } ,      { "type" : "uri", "value" : "http://dbpedia.org/resource/Betsy_Brantley" } ,      { "type" : "uri", "value" : "http://dbpedia.org/resource/Ving_Rhames" } ,      { "type" : "uri", "value" : "http://dbpedia.org/resource/Platoon" } ,      { "type" : "uri", "value" : "http://dbpedia.org/resource/American_Broadcasting_Company" } ,      { "type" : "uri", "value" : "http://dbpedia.org/resource/Paint_It_Black" } ,      { "type" : "uri", "value" : "http://dbpedia.org/resource/Combat!" } ,      { "type" : "uri", "value" : "http://dbpedia.org/resource/Category:Television_series_based_on_actual_events" } ,      { "type" : "uri", "value" : "http://dbpedia.org/resource/Lee_Majors" } ,      { "type" : "uri", "value" : "http://dbpedia.org/resource/Terence_Knox" } ,      { "type" : "uri", "value" : "http://dbpedia.org/resource/Search_and_destroy" } ,      { "type" : "uri", "value" : "http://dbpedia.org/resource/Carl_Weathers" } ,      { "type" : "uri", "value" : "http://dbpedia.org/resource/Ram\u00F3n_Franco_(actor)" } ,      { "type" : "uri", "value" : "http://dbpedia.org/resource/Oliver_Stone" } ,      { "type" : "uri", "value" : "http://dbpedia.org/resource/Company_(military_unit)" } ,      { "type" : "uri", "value" : "http://dbpedia.org/resource/Saigon" } ,      { "type" : "uri", "value" : "http://dbpedia.org/resource/Melora_Hardin" } ,      { "type" : "uri", "value" : "http://dbpedia.org/resource/Classic_rock" } ,      { "type" : "uri", "value" : "http://dbpedia.org/resource/Jimi_Hendrix" } ,      { "type" : "uri", "value" : "http://dbpedia.org/resource/Faith" } ,      { "type" : "uri", "value" : "http://dbpedia.org/resource/Creedence_Clearwater_Revival" } ,      { "type" : "uri", "value" : "http://dbpedia.org/resource/South_Vietnam" } ,      { "type" : "uri", "value" : "http://dbpedia.org/resource/Tour_of_Duty_(season_3)" } ,      { "type" : "uri", "value" : "http://dbpedia.org/resource/Los_Angeles,_California" } ,      { "type" : "uri", "value" : "http://dbpedia.org/resource/Operation_Ivory_Coast" } ,      { "type" : "uri", "value" : "http://dbpedia.org/resource/Primetime_Emmy_Award_for_Outstanding_Sound_Mixing_for_a_Comedy_or_Drama_Series_(One-Hour)" } ,      { "type" : "uri", "value" : "http://dbpedia.org/resource/Michael_Fairman" } ,      { "type" : "uri", "value" : "http://dbpedia.org/resource/China_Beach" } ,      { "type" : "uri", "value" : "http://dbpedia.org/resource/1988\u201389_United_States_network_television_schedule" } ,      { "type" : "uri", "value" : "http://dbpedia.org/resource/1989\u201390_United_States_network_television_schedule" } ,      { "type" : "uri", "value" : "http://dbpedia.org/resource/Joseph_Conlan" } ,      { "type" : "uri", "value" : "http://dbpedia.org/resource/Kyle_Chandler" } ,      { "type" : "uri", "value" : "http://dbpedia.org/resource/Bill_L._Norton" } ,      { "type" : "uri", "value" : "http://dbpedia.org/resource/Peter_Vogt_(actor)" } ,      { "type" : "uri", "value" : "http://dbpedia.org/resource/Kelly_Hu" } ,      { "type" : "uri", "value" : "http://dbpedia.org/resource/John_Dye" } ,      { "type" : "uri", "value" : "http://dbpedia.org/resource/Patrick_Kilpatrick" } ,      { "type" : "uri", "value" : "http://dbpedia.org/resource/Disney-ABC_International_Television" } ,      { "type" : "uri", "value" : "http://dbpedia.org/resource/1987\u201388_United_States_network_television_schedule" } ,      { "type" : "uri", "value" : "http://dbpedia.org/resource/United_Service_Organizations" } ,      { "type" : "uri", "value" : "http://dbpedia.org/resource/Studies_and_Observations_Group" } ,      { "type" : "uri", "value" : "http://dbpedia.org/resource/Nielsen_ratings" } ,      { "type" : "uri", "value" : "http://dbpedia.org/resource/Monaural" } ,      { "type" : "uri", "value" : "http://dbpedia.org/resource/Mako_(actor)" } ,      { "type" : "uri", "value" : "http://dbpedia.org/resource/Cambodia" } ,      { "type" : "uri", "value" : "http://dbpedia.org/resource/Tour_of_Duty_(Season_3)" } ,      { "type" : "uri", "value" : "http://dbpedia.org/resource/Angela_Bassett" } ] ,    "http://dbpedia.org/property/wikiPageUsesTemplate" : [ { "type" : "uri", "value" : "http://dbpedia.org/resource/Template:IMDb_title" } ,      { "type" : "uri", "value" : "http://dbpedia.org/resource/Template:Abbr" } ,      { "type" : "uri", "value" : "http://dbpedia.org/resource/Template:Series_overview" } ,      { "type" : "uri", "value" : "http://dbpedia.org/resource/Template:Infobox_television" } ,      { "type" : "uri", "value" : "http://dbpedia.org/resource/Template:Short_description" } ,      { "type" : "uri", "value" : "http://dbpedia.org/resource/Template:Citation_needed" } ,      { "type" : "uri", "value" : "http://dbpedia.org/resource/Template:End_date" } ,      { "type" : "uri", "value" : "http://dbpedia.org/resource/Template:Ubl" } ,      { "type" : "uri", "value" : "http://dbpedia.org/resource/Template:Other_uses" } ,      { "type" : "uri", "value" : "http://dbpedia.org/resource/Template:N/a" } ,      { "type" : "uri", "value" : "http://dbpedia.org/resource/Template:More_citations_needed" } ,      { "type" : "uri", "value" : "http://dbpedia.org/resource/Template:TOC_limit" } ,      { "type" : "uri", "value" : "http://dbpedia.org/resource/Template:Wikiquote" } ,      { "type" : "uri", "value" : "http://dbpedia.org/resource/Template:'" } ,      { "type" : "uri", "value" : "http://dbpedia.org/resource/Template:Start_date" } ,      { "type" : "uri", "value" : "http://dbpedia.org/resource/Template:Reflist" } ] ,    "http://dbpedia.org/property/wordnet_type" : [ { "type" : "uri", "value" : "http://www.w3.org/2006/03/wn/wn20/instances/synset-telecast-noun-1" } ] ,    "http://dbpedia.org/ontology/thumbnail" : [ { "type" : "uri", "value" : "http://commons.wikimedia.org/wiki/Special:FilePath/Tour_of_duty_tv_series.jpg?width=300" } ] ,    "http://dbpedia.org/ontology/wikiPageRevisionID" : [ { "type" : "literal", "value" : 1114310726 , "datatype" : "http://www.w3.org/2001/XMLSchema#integer" } ] ,    "http://dbpedia.org/property/country" : [ { "type" : "literal", "value" : "United States" , "lang" : "en" } ] ,    "http://dbpedia.org/ontology/wikiPageExternalLink" : [ { "type" : "uri", "value" : "https://web.archive.org/web/20120225032057/http:/www.totalfanhub.com/tour-of-duty/" } ,      { "type" : "uri", "value" : "http://www.hum90.com" } ] ,    "http://dbpedia.org/ontology/wikiPageLength" : [ { "type" : "literal", "value" : "28457" , "datatype" : "http://www.w3.org/2001/XMLSchema#nonNegativeInteger" } ] ,    "http://dbpedia.org/ontology/wikiPageID" : [ { "type" : "literal", "value" : 2009237 , "datatype" : "http://www.w3.org/2001/XMLSchema#integer" } ] ,    "http://dbpedia.org/property/id" : [ { "type" : "literal", "value" : 92468 , "datatype" : "http://www.w3.org/2001/XMLSchema#integer" } ] ,    "http://dbpedia.org/ontology/distributor" : [ { "type" : "uri", "value" : "http://dbpedia.org/resource/20th_Century_Fox_Television" } ,      { "type" : "uri", "value" : "http://dbpedia.org/resource/Disney-ABC_International_Television" } ] ,    "http://dbpedia.org/property/language" : [ { "type" : "literal", "value" : "English" , "lang" : "en" } ] ,    "http://dbpedia.org/property/distributor" : [ { "type" : "literal", "value" : 20 , "datatype" : "http://www.w3.org/2001/XMLSchema#integer" } ] ,    "http://dbpedia.org/ontology/imdbId" : [ { "type" : "literal", "value" : "0092468" } ] ,    "http://dbpedia.org/ontology/runtime" : [ { "type" : "literal", "value" : -2940 , "datatype" : "http://www.w3.org/2001/XMLSchema#double" } ] ,    "http://dbpedia.org/property/title" : [ { "type" : "literal", "value" : "Tour of Duty" , "lang" : "en" } ] ,    "http://dbpedia.org/property/runtime" : [ { "type" : "literal", "value" : "-2940.0" , "datatype" : "http://dbpedia.org/datatype/second" } ] ,    "http://dbpedia.org/property/producer" : [ { "type" : "uri", "value" : "http://dbpedia.org/resource/Zev_Braun" } ] ,    "http://dbpedia.org/ontology/producer" : [ { "type" : "uri", "value" : "http://dbpedia.org/resource/Zev_Braun" } ] ,    "http://dbpedia.org/ontology/Work/runtime" : [ { "type" : "literal", "value" : "-49.0" , "datatype" : "http://dbpedia.org/datatype/minute" } ] ,    "http://dbpedia.org/property/caption" : [ { "type" : "literal", "value" : "Title card" , "lang" : "en" } ] ,    "http://dbpedia.org/property/music" : [ { "type" : "uri", "value" : "http://dbpedia.org/resource/Joseph_Conlan" } ] ,    "http://www.w3.org/2002/07/owl#sameAs" : [ { "type" : "uri", "value" : "http://nl.dbpedia.org/resource/Tour_of_Duty" } ,      { "type" : "uri", "value" : "http://rdf.freebase.com/ns/m.06dr44" } ,      { "type" : "uri", "value" : "http://es.dbpedia.org/resource/Tour_of_Duty" } ,      { "type" : "uri", "value" : "http://de.dbpedia.org/resource/NAM_\u2013_Dienst_in_Vietnam" } ,      { "type" : "uri", "value" : "http://it.dbpedia.org/resource/Vietnam_addio" } ,      { "type" : "uri", "value" : "http://ru.dbpedia.org/resource/\u0421\u043B\u0443\u0436\u0435\u0431\u043D\u0430\u044F_\u043A\u043E\u043C\u0430\u043D\u0434\u0438\u0440\u043E\u0432\u043A\u0430_(\u0442\u0435\u043B\u0435\u0441\u0435\u0440\u0438\u0430\u043B)" } ,      { "type" : "uri", "value" : "http://cs.dbpedia.org/resource/\u010Ceta_v_akci" } ,      { "type" : "uri", "value" : "http://www.wikidata.org/entity/Q1959738" } ,      { "type" : "uri", "value" : "http://dbpedia.org/resource/Tour_of_Duty_(TV_series)" } ,      { "type" : "uri", "value" : "https://global.dbpedia.org/id/rwei" } ,      { "type" : "uri", "value" : "http://ko.dbpedia.org/resource/\uBA38\uB098\uBA3C_\uC815\uAE00" } ,      { "type" : "uri", "value" : "http://pt.dbpedia.org/resource/Combate_no_Vietn\u00E3_(s\u00E9rie_de_televis\u00E3o)" } ,      { "type" : "uri", "value" : "http://sv.dbpedia.org/resource/Pluton_B_i_Vietnam" } ,      { "type" : "uri", "value" : "http://yago-knowledge.org/resource/Tour_of_Duty_(TV_series)" } ,      { "type" : "uri", "value" : "http://fr.dbpedia.org/resource/L'Enfer_du_devoir_(s\u00E9rie_t\u00E9l\u00E9vis\u00E9e)" } ] ,    "http://purl.org/linguistics/gold/hypernym" : [ { "type" : "uri", "value" : "http://dbpedia.org/resource/Series" } ] ,    "http://www.w3.org/ns/prov#wasDerivedFrom" : [ { "type" : "uri", "value" : "http://en.wikipedia.org/wiki/Tour_of_Duty_(TV_series)?oldid=1114310726&ns=0" } ] ,    "http://xmlns.com/foaf/0.1/isPrimaryTopicOf" : [ { "type" : "uri", "value" : "http://en.wikipedia.org/wiki/Tour_of_Duty_(TV_series)" } ] ,    "http://dbpedia.org/property/color" : [ { "type" : "literal", "value" : "#ff0000" , "lang" : "en" } ,      { "type" : "literal", "value" : "#0000ff" , "lang" : "en" } ,      { "type" : "literal", "value" : "#00ff00" , "lang" : "en" } ] ,    "http://dbpedia.org/property/episodes" : [ { "type" : "literal", "value" : 16 , "datatype" : "http://www.w3.org/2001/XMLSchema#integer" } ,      { "type" : "literal", "value" : 21 , "datatype" : "http://www.w3.org/2001/XMLSchema#integer" } ] ,    "http://dbpedia.org/property/end" : [ { "type" : "literal", "value" : "1990-04-28" , "datatype" : "http://www.w3.org/2001/XMLSchema#date" } ,      { "type" : "literal", "value" : "1989-05-16" , "datatype" : "http://www.w3.org/2001/XMLSchema#date" } ,      { "type" : "literal", "value" : "1988-04-30" , "datatype" : "http://www.w3.org/2001/XMLSchema#date" } ] ,    "http://dbpedia.org/property/start" : [ { "type" : "literal", "value" : "1989-09-23" , "datatype" : "http://www.w3.org/2001/XMLSchema#date" } ,      { "type" : "literal", "value" : "1989-01-03" , "datatype" : "http://www.w3.org/2001/XMLSchema#date" } ,      { "type" : "literal", "value" : "1987-09-24" , "datatype" : "http://www.w3.org/2001/XMLSchema#date" } ] ,    "http://dbpedia.org/ontology/genre" : [ { "type" : "uri", "value" : "http://dbpedia.org/resource/Military_drama" } ] ,    "http://dbpedia.org/property/genre" : [ { "type" : "uri", "value" : "http://dbpedia.org/resource/Military_drama" } ] ,    "http://dbpedia.org/ontology/executiveProducer" : [ { "type" : "uri", "value" : "http://dbpedia.org/resource/Ronald_L._Schwary" } ,      { "type" : "uri", "value" : "http://dbpedia.org/resource/L._Travis_Clark" } ] ,    "http://dbpedia.org/property/numEpisodes" : [ { "type" : "literal", "value" : 58 , "datatype" : "http://www.w3.org/2001/XMLSchema#integer" } ] ,    "http://dbpedia.org/property/executiveProducer" : [ { "type" : "literal", "value" : "Steve Duncan" , "lang" : "en" } ,      { "type" : "literal", "value" : "L. Travis Clark" , "lang" : "en" } ,      { "type" : "uri", "value" : "http://dbpedia.org/resource/Ronald_L._Schwary" } ] ,    "http://dbpedia.org/property/firstAired" : [ { "type" : "literal", "value" : "1987-09-24" , "datatype" : "http://www.w3.org/2001/XMLSchema#date" } ] ,    "http://dbpedia.org/property/lastAired" : [ { "type" : "literal", "value" : "1990-04-28" , "datatype" : "http://www.w3.org/2001/XMLSchema#date" } ] ,    "http://dbpedia.org/ontology/completionDate" : [ { "type" : "literal", "value" : "1990-04-28" , "datatype" : "http://www.w3.org/2001/XMLSchema#date" } ] ,    "http://dbpedia.org/ontology/numberOfEpisodes" : [ { "type" : "literal", "value" : "58" , "datatype" : "http://www.w3.org/2001/XMLSchema#nonNegativeInteger" } ] ,    "http://dbpedia.org/ontology/numberOfSeasons" : [ { "type" : "literal", "value" : "3" , "datatype" : "http://www.w3.org/2001/XMLSchema#nonNegativeInteger" } ] ,    "http://dbpedia.org/property/numSeasons" : [ { "type" : "literal", "value" : 3 , "datatype" : "http://www.w3.org/2001/XMLSchema#integer" } ] ,    "http://dbpedia.org/property/link" : [ { "type" : "literal", "value" : "Tour_of_Duty_#Episodes" , "lang" : "en" } ] ,    "http://dbpedia.org/property/audioFormat" : [ { "type" : "uri", "value" : "http://dbpedia.org/resource/Monaural" } ] ,    "http://dbpedia.org/property/network" : [ { "type" : "uri", "value" : "http://dbpedia.org/resource/CBS" } ] ,    "http://dbpedia.org/ontology/network" : [ { "type" : "uri", "value" : "http://dbpedia.org/resource/CBS" } ] ,    "http://dbpedia.org/ontology/format" : [ { "type" : "uri", "value" : "http://dbpedia.org/resource/Monaural" } ] ,    "http://dbpedia.org/ontology/releaseDate" : [ { "type" : "literal", "value" : "1987-09-24" , "datatype" : "http://www.w3.org/2001/XMLSchema#date" } ] } ,  "http://dbpedia.org/resource/Jim_Fitzpatrick_(actor)" : { "http://dbpedia.org/ontology/wikiPageWikiLink" : [ { "type" : "uri", "value" : "http://dbpedia.org/resource/Tour_of_Duty_(TV_series)" } ] } ,  "http://dbpedia.org/resource/John_D._LeMay" : { "http://dbpedia.org/ontology/wikiPageWikiLink" : [ { "type" : "uri", "value" : "http://dbpedia.org/resource/Tour_of_Duty_(TV_series)" } ] } ,  "http://dbpedia.org/resource/List_of_top_25_albums_for_1988_in_Australia" : { "http://dbpedia.org/ontology/wikiPageWikiLink" : [ { "type" : "uri", "value" : "http://dbpedia.org/resource/Tour_of_Duty_(TV_series)" } ] } ,  "http://dbpedia.org/resource/Bop_TV" : { "http://dbpedia.org/ontology/wikiPageWikiLink" : [ { "type" : "uri", "value" : "http://dbpedia.org/resource/Tour_of_Duty_(TV_series)" } ] } ,  "http://dbpedia.org/resource/Combat!" : { "http://dbpedia.org/ontology/wikiPageWikiLink" : [ { "type" : "uri", "value" : "http://dbpedia.org/resource/Tour_of_Duty_(TV_series)" } ] } ,  "http://en.wikipedia.org/wiki/Tour_of_Duty_(TV_series)" : { "http://xmlns.com/foaf/0.1/primaryTopic" : [ { "type" : "uri", "value" : "http://dbpedia.org/resource/Tour_of_Duty_(TV_series)" } ] } ,  "http://dbpedia.org/resource/Kevin_Conroy" : { "http://dbpedia.org/ontology/wikiPageWikiLink" : [ { "type" : "uri", "value" : "http://dbpedia.org/resource/Tour_of_Duty_(TV_series)" } ] } ,  "http://dbpedia.org/resource/Stan_Foster" : { "http://dbpedia.org/ontology/wikiPageWikiLink" : [ { "type" : "uri", "value" : "http://dbpedia.org/resource/Tour_of_Duty_(TV_series)" } ] } ,  "http://dbpedia.org/resource/Talia_Balsam" : { "http://dbpedia.org/ontology/wikiPageWikiLink" : [ { "type" : "uri", "value" : "http://dbpedia.org/resource/Tour_of_Duty_(TV_series)" } ] } ,  "http://dbpedia.org/resource/2022_in_American_television" : { "http://dbpedia.org/ontology/wikiPageWikiLink" : [ { "type" : "uri", "value" : "http://dbpedia.org/resource/Tour_of_Duty_(TV_series)" } ] } ,  "http://dbpedia.org/resource/2018_deaths_in_American_television" : { "http://dbpedia.org/ontology/wikiPageWikiLink" : [ { "type" : "uri", "value" : "http://dbpedia.org/resource/Tour_of_Duty_(TV_series)" } ] } ,  "http://dbpedia.org/resource/1948_in_television" : { "http://dbpedia.org/ontology/wikiPageWikiLink" : [ { "type" : "uri", "value" : "http://dbpedia.org/resource/Tour_of_Duty_(TV_series)" } ] } ,  "http://dbpedia.org/resource/The_Bradys" : { "http://dbpedia.org/ontology/wikiPageWikiLink" : [ { "type" : "uri", "value" : "http://dbpedia.org/resource/Tour_of_Duty_(TV_series)" } ] } ,  "http://dbpedia.org/resource/New_World_Pictures" : { "http://dbpedia.org/ontology/wikiPageWikiLink" : [ { "type" : "uri", "value" : "http://dbpedia.org/resource/Tour_of_Duty_(TV_series)" } ] } ,  "http://dbpedia.org/resource/Danny_Nucci" : { "http://dbpedia.org/ontology/wikiPageWikiLink" : [ { "type" : "uri", "value" : "http://dbpedia.org/resource/Tour_of_Duty_(TV_series)" } ] } ,  "http://dbpedia.org/resource/Krista_Errickson" : { "http://dbpedia.org/ontology/wikiPageWikiLink" : [ { "type" : "uri", "value" : "http://dbpedia.org/resource/Tour_of_Duty_(TV_series)" } ] } ,  "http://dbpedia.org/resource/Peter_Murnik" : { "http://dbpedia.org/ontology/wikiPageWikiLink" : [ { "type" : "uri", "value" : "http://dbpedia.org/resource/Tour_of_Duty_(TV_series)" } ] } ,  "http://dbpedia.org/resource/Les_Lannom" : { "http://dbpedia.org/ontology/wikiPageWikiLink" : [ { "type" : "uri", "value" : "http://dbpedia.org/resource/Tour_of_Duty_(TV_series)" } ] } ,  "http://dbpedia.org/resource/Baoan_Coleman" : { "http://dbpedia.org/ontology/wikiPageWikiLink" : [ { "type" : "uri", "value" : "http://dbpedia.org/resource/Tour_of_Duty_(TV_series)" } ] } ,  "http://dbpedia.org/resource/Michael_Carmine" : { "http://dbpedia.org/ontology/wikiPageWikiLink" : [ { "type" : "uri", "value" : "http://dbpedia.org/resource/Tour_of_Duty_(TV_series)" } ] } ,  "http://dbpedia.org/resource/Richard_Brooks_(actor)" : { "http://dbpedia.org/ontology/wikiPageWikiLink" : [ { "type" : "uri", "value" : "http://dbpedia.org/resource/Tour_of_Duty_(TV_series)" } ] } ,  "http://dbpedia.org/resource/Kelly_Hu" : { "http://dbpedia.org/ontology/wikiPageWikiLink" : [ { "type" : "uri", "value" : "http://dbpedia.org/resource/Tour_of_Duty_(TV_series)" } ] } ,  "http://dbpedia.org/resource/Nathan_Jung" : { "http://dbpedia.org/ontology/wikiPageWikiLink" : [ { "type" : "uri", "value" : "http://dbpedia.org/resource/Tour_of_Duty_(TV_series)" } ] } ,  "http://dbpedia.org/resource/Terence_Knox" : { "http://dbpedia.org/ontology/wikiPageWikiLink" : [ { "type" : "uri", "value" : "http://dbpedia.org/resource/Tour_of_Duty_(TV_series)" } ] } ,  "http://dbpedia.org/resource/Jim_Beaver" : { "http://dbpedia.org/ontology/wikiPageWikiLink" : [ { "type" : "uri", "value" : "http://dbpedia.org/resource/Tour_of_Duty_(TV_series)" } ] } ,  "http://dbpedia.org/resource/Tamlyn_Tomita" : { "http://dbpedia.org/ontology/wikiPageWikiLink" : [ { "type" : "uri", "value" : "http://dbpedia.org/resource/Tour_of_Duty_(TV_series)" } ] } ,  "http://dbpedia.org/resource/Penny_Johnson_Jerald" : { "http://dbpedia.org/ontology/wikiPageWikiLink" : [ { "type" : "uri", "value" : "http://dbpedia.org/resource/Tour_of_Duty_(TV_series)" } ] } ,  "http://dbpedia.org/resource/Malibu_Creek_State_Park" : { "http://dbpedia.org/ontology/wikiPageWikiLink" : [ { "type" : "uri", "value" : "http://dbpedia.org/resource/Tour_of_Duty_(TV_series)" } ] } ,  "http://dbpedia.org/resource/Rob_Garrison" : { "http://dbpedia.org/ontology/wikiPageWikiLink" : [ { "type" : "uri", "value" : "http://dbpedia.org/resource/Tour_of_Duty_(TV_series)" } ] } ,  "http://dbpedia.org/resource/1988\u201389_United_States_network_television_schedule" : { "http://dbpedia.org/ontology/wikiPageWikiLink" : [ { "type" : "uri", "value" : "http://dbpedia.org/resource/Tour_of_Duty_(TV_series)" } ] } ,  "http://dbpedia.org/resource/1989\u201390_United_States_network_television_schedule" : { "http://dbpedia.org/ontology/wikiPageWikiLink" : [ { "type" : "uri", "value" : "http://dbpedia.org/resource/Tour_of_Duty_(TV_series)" } ] } ,  "http://dbpedia.org/resource/Albie_Selznick" : { "http://dbpedia.org/ontology/wikiPageWikiLink" : [ { "type" : "uri", "value" : "http://dbpedia.org/resource/Tour_of_Duty_(TV_series)" } ] } ,  "http://dbpedia.org/resource/Tad_Horino" : { "http://dbpedia.org/ontology/wikiPageWikiLink" : [ { "type" : "uri", "value" : "http://dbpedia.org/resource/Tour_of_Duty_(TV_series)" } ] } ,  "http://dbpedia.org/resource/List_of_television_episodes_titled_Pilot" : { "http://dbpedia.org/ontology/wikiPageWikiLink" : [ { "type" : "uri", "value" : "http://dbpedia.org/resource/Tour_of_Duty_(TV_series)" } ] } ,  "http://dbpedia.org/resource/List_of_television_theme_music" : { "http://dbpedia.org/ontology/wikiPageWikiLink" : [ { "type" : "uri", "value" : "http://dbpedia.org/resource/Tour_of_Duty_(TV_series)" } ] } ,  "http://dbpedia.org/resource/Chi_Muoi_Lo" : { "http://dbpedia.org/ontology/wikiPageWikiLink" : [ { "type" : "uri", "value" : "http://dbpedia.org/resource/Tour_of_Duty_(TV_series)" } ] } ,  "http://dbpedia.org/resource/1968_in_television" : { "http://dbpedia.org/ontology/wikiPageWikiLink" : [ { "type" : "uri", "value" : "http://dbpedia.org/resource/Tour_of_Duty_(TV_series)" } ] } ,  "http://dbpedia.org/resource/We_Gotta_Get_Out_of_This_Place" : { "http://dbpedia.org/ontology/wikiPageWikiLink" : [ { "type" : "uri", "value" : "http://dbpedia.org/resource/Tour_of_Duty_(TV_series)" } ] } ,  "http://dbpedia.org/resource/Ted_King_(actor)" : { "http://dbpedia.org/ontology/wikiPageWikiLink" : [ { "type" : "uri", "value" : "http://dbpedia.org/resource/Tour_of_Duty_(TV_series)" } ] } ,  "http://dbpedia.org/resource/Bob_Boykin" : { "http://dbpedia.org/ontology/wikiPageWikiLink" : [ { "type" : "uri", "value" : "http://dbpedia.org/resource/Tour_of_Duty_(TV_series)" } ] } ,  "http://dbpedia.org/resource/List_of_war_films_and_TV_specials_set_between_1945_and_2001" : { "http://dbpedia.org/ontology/wikiPageWikiLink" : [ { "type" : "uri", "value" : "http://dbpedia.org/resource/Tour_of_Duty_(TV_series)" } ] } ,  "http://dbpedia.org/resource/Bill_L._Norton" : { "http://dbpedia.org/ontology/wikiPageWikiLink" : [ { "type" : "uri", "value" : "http://dbpedia.org/resource/Tour_of_Duty_(TV_series)" } ] } ,  "http://dbpedia.org/resource/Rob_Moran" : { "http://dbpedia.org/ontology/wikiPageWikiLink" : [ { "type" : "uri", "value" : "http://dbpedia.org/resource/Tour_of_Duty_(TV_series)" } ] } ,  "http://dbpedia.org/resource/Joseph_Conlan" : { "http://dbpedia.org/ontology/wikiPageWikiLink" : [ { "type" : "uri", "value" : "http://dbpedia.org/resource/Tour_of_Duty_(TV_series)" } ] } ,  "http://dbpedia.org/resource/John_Dye" : { "http://dbpedia.org/ontology/wikiPageWikiLink" : [ { "type" : "uri", "value" : "http://dbpedia.org/resource/Tour_of_Duty_(TV_series)" } ] } ,  "http://dbpedia.org/resource/Ram\u00F3n_Franco_(actor)" : { "http://dbpedia.org/ontology/wikiPageWikiLink" : [ { "type" : "uri", "value" : "http://dbpedia.org/resource/Tour_of_Duty_(TV_series)" } ] } ,  "http://dbpedia.org/resource/Rebel_Love" : { "http://dbpedia.org/ontology/wikiPageWikiLink" : [ { "type" : "uri", "value" : "http://dbpedia.org/resource/Tour_of_Duty_(TV_series)" } ] } ,  "http://dbpedia.org/resource/Cameron_Bancroft_(actor)" : { "http://dbpedia.org/ontology/wikiPageWikiLink" : [ { "type" : "uri", "value" : "http://dbpedia.org/resource/Tour_of_Duty_(TV_series)" } ] } ,  "http://dbpedia.org/resource/1990_in_Spanish_television" : { "http://dbpedia.org/ontology/wikiPageWikiLink" : [ { "type" : "uri", "value" : "http://dbpedia.org/resource/Tour_of_Duty_(TV_series)" } ] } ,  "http://dbpedia.org/resource/Schofield_Barracks" : { "http://dbpedia.org/ontology/wikiPageWikiLink" : [ { "type" : "uri", "value" : "http://dbpedia.org/resource/Tour_of_Duty_(TV_series)" } ] } ,  "http://dbpedia.org/resource/Jon_Cypher" : { "http://dbpedia.org/ontology/wikiPageWikiLink" : [ { "type" : "uri", "value" : "http://dbpedia.org/resource/Tour_of_Duty_(TV_series)" } ] } ,  "http://dbpedia.org/resource/List_of_programs_broadcast_by_Seven_Network" : { "http://dbpedia.org/ontology/wikiPageWikiLink" : [ { "type" : "uri", "value" : "http://dbpedia.org/resource/Tour_of_Duty_(TV_series)" } ] } ,  "http://dbpedia.org/resource/Michael_Cavanaugh_(actor)" : { "http://dbpedia.org/ontology/wikiPageWikiLink" : [ { "type" : "uri", "value" : "http://dbpedia.org/resource/Tour_of_Duty_(TV_series)" } ] } ,  "http://dbpedia.org/resource/Malcolm-Jamal_Warner" : { "http://dbpedia.org/ontology/wikiPageWikiLink" : [ { "type" : "uri", "value" : "http://dbpedia.org/resource/Tour_of_Duty_(TV_series)" } ] } ,  "http://dbpedia.org/resource/Veronica_TV" : { "http://dbpedia.org/ontology/wikiPageWikiLink" : [ { "type" : "uri", "value" : "http://dbpedia.org/resource/Tour_of_Duty_(TV_series)" } ] } ,  "http://dbpedia.org/resource/James_Jude_Courtney" : { "http://dbpedia.org/ontology/wikiPageWikiLink" : [ { "type" : "uri", "value" : "http://dbpedia.org/resource/Tour_of_Duty_(TV_series)" } ] } ,  "http://dbpedia.org/resource/Nigerian_Television_Authority" : { "http://dbpedia.org/ontology/wikiPageWikiLink" : [ { "type" : "uri", "value" : "http://dbpedia.org/resource/Tour_of_Duty_(TV_series)" } ] } ,  "http://dbpedia.org/resource/Mako_(actor)" : { "http://dbpedia.org/ontology/wikiPageWikiLink" : [ { "type" : "uri", "value" : "http://dbpedia.org/resource/Tour_of_Duty_(TV_series)" } ] } ,  "http://dbpedia.org/resource/Bill_Moseley" : { "http://dbpedia.org/ontology/wikiPageWikiLink" : [ { "type" : "uri", "value" : "http://dbpedia.org/resource/Tour_of_Duty_(TV_series)" } ] } ,  "http://dbpedia.org/resource/Neil_Flynn" : { "http://dbpedia.org/ontology/wikiPageWikiLink" : [ { "type" : "uri", "value" : "http://dbpedia.org/resource/Tour_of_Duty_(TV_series)" } ] } ,  "http://dbpedia.org/resource/Mark_Rolston" : { "http://dbpedia.org/ontology/wikiPageWikiLink" : [ { "type" : "uri", "value" : "http://dbpedia.org/resource/Tour_of_Duty_(TV_series)" } ] } ,  "http://dbpedia.org/resource/Larry_Poindexter" : { "http://dbpedia.org/ontology/wikiPageWikiLink" : [ { "type" : "uri", "value" : "http://dbpedia.org/resource/Tour_of_Duty_(TV_series)" } ] } ,  "http://dbpedia.org/resource/ZBC_TV" : { "http://dbpedia.org/ontology/wikiPageWikiLink" : [ { "type" : "uri", "value" : "http://dbpedia.org/resource/Tour_of_Duty_(TV_series)" } ] } ,  "http://dbpedia.org/resource/Deaths_in_October_2019" : { "http://dbpedia.org/ontology/wikiPageWikiLink" : [ { "type" : "uri", "value" : "http://dbpedia.org/resource/Tour_of_Duty_(TV_series)" } ] } ,  "http://dbpedia.org/resource/Tour_of_Duty_(tv_series)" : { "http://dbpedia.org/ontology/wikiPageWikiLink" : [ { "type" : "uri", "value" : "http://dbpedia.org/resource/Tour_of_Duty_(TV_series)" } ] ,    "http://dbpedia.org/ontology/wikiPageRedirects" : [ { "type" : "uri", "value" : "http://dbpedia.org/resource/Tour_of_Duty_(TV_series)" } ] } ,  "http://dbpedia.org/resource/Lee_Majors" : { "http://dbpedia.org/ontology/wikiPageWikiLink" : [ { "type" : "uri", "value" : "http://dbpedia.org/resource/Tour_of_Duty_(TV_series)" } ] } ,  "http://dbpedia.org/resource/Pamela_Gidley" : { "http://dbpedia.org/ontology/wikiPageWikiLink" : [ { "type" : "uri", "value" : "http://dbpedia.org/resource/Tour_of_Duty_(TV_series)" } ] } ,  "http://dbpedia.org/resource/James_L._Conway" : { "http://dbpedia.org/ontology/wikiPageWikiLink" : [ { "type" : "uri", "value" : "http://dbpedia.org/resource/Tour_of_Duty_(TV_series)" } ] } ,  "http://dbpedia.org/resource/Tim_Thomerson" : { "http://dbpedia.org/ontology/wikiPageWikiLink" : [ { "type" : "uri", "value" : "http://dbpedia.org/resource/Tour_of_Duty_(TV_series)" } ] } ,  "http://dbpedia.org/resource/Trevor_Goddard" : { "http://dbpedia.org/ontology/wikiPageWikiLink" : [ { "type" : "uri", "value" : "http://dbpedia.org/resource/Tour_of_Duty_(TV_series)" } ] } ,  "http://dbpedia.org/resource/List_of_programmes_broadcast_by_Channel_5_(Singapore)" : { "http://dbpedia.org/ontology/wikiPageWikiLink" : [ { "type" : "uri", "value" : "http://dbpedia.org/resource/Tour_of_Duty_(TV_series)" } ] } ,  "http://dbpedia.org/resource/Peter_Neptune" : { "http://dbpedia.org/ontology/wikiPageWikiLink" : [ { "type" : "uri", "value" : "http://dbpedia.org/resource/Tour_of_Duty_(TV_series)" } ] } ,  "http://dbpedia.org/resource/Penny_Peyser" : { "http://dbpedia.org/ontology/wikiPageWikiLink" : [ { "type" : "uri", "value" : "http://dbpedia.org/resource/Tour_of_Duty_(TV_series)" } ] } ,  "http://dbpedia.org/resource/Tommy_Lee_Wallace" : { "http://dbpedia.org/ontology/wikiPageWikiLink" : [ { "type" : "uri", "value" : "http://dbpedia.org/resource/Tour_of_Duty_(TV_series)" } ] } ,  "http://dbpedia.org/resource/Military_payment_certificate" : { "http://dbpedia.org/ontology/wikiPageWikiLink" : [ { "type" : "uri", "value" : "http://dbpedia.org/resource/Tour_of_Duty_(TV_series)" } ] } ,  "http://dbpedia.org/resource/David_Alan_Grier" : { "http://dbpedia.org/ontology/wikiPageWikiLink" : [ { "type" : "uri", "value" : "http://dbpedia.org/resource/Tour_of_Duty_(TV_series)" } ] } ,  "http://dbpedia.org/resource/Tia_Carrere" : { "http://dbpedia.org/ontology/wikiPageWikiLink" : [ { "type" : "uri", "value" : "http://dbpedia.org/resource/Tour_of_Duty_(TV_series)" } ] } ,  "http://dbpedia.org/resource/Clyde_Kusatsu" : { "http://dbpedia.org/ontology/wikiPageWikiLink" : [ { "type" : "uri", "value" : "http://dbpedia.org/resource/Tour_of_Duty_(TV_series)" } ] } ,  "http://dbpedia.org/resource/Keone_Young" : { "http://dbpedia.org/ontology/wikiPageWikiLink" : [ { "type" : "uri", "value" : "http://dbpedia.org/resource/Tour_of_Duty_(TV_series)" } ] } ,  "http://dbpedia.org/resource/Anderson_(surname)" : { "http://dbpedia.org/ontology/wikiPageWikiLink" : [ { "type" : "uri", "value" : "http://dbpedia.org/resource/Tour_of_Duty_(TV_series)" } ] } ,  "http://dbpedia.org/resource/1988_in_Australian_television" : { "http://dbpedia.org/ontology/wikiPageWikiLink" : [ { "type" : "uri", "value" : "http://dbpedia.org/resource/Tour_of_Duty_(TV_series)" } ] } ,  "http://dbpedia.org/resource/Eric_Bruskotter" : { "http://dbpedia.org/ontology/wikiPageWikiLink" : [ { "type" : "uri", "value" : "http://dbpedia.org/resource/Tour_of_Duty_(TV_series)" } ] } ,  "http://dbpedia.org/resource/Skip_Stellrecht" : { "http://dbpedia.org/ontology/wikiPageWikiLink" : [ { "type" : "uri", "value" : "http://dbpedia.org/resource/Tour_of_Duty_(TV_series)" } ] } ,  "http://dbpedia.org/resource/Michael_Madsen_filmography" : { "http://dbpedia.org/ontology/wikiPageWikiLink" : [ { "type" : "uri", "value" : "http://dbpedia.org/resource/Tour_of_Duty_(TV_series)" } ] } ,  "http://dbpedia.org/resource/William_Russ" : { "http://dbpedia.org/ontology/wikiPageWikiLink" : [ { "type" : "uri", "value" : "http://dbpedia.org/resource/Tour_of_Duty_(TV_series)" } ] } ,  "http://dbpedia.org/resource/Deaths_in_January_2011" : { "http://dbpedia.org/ontology/wikiPageWikiLink" : [ { "type" : "uri", "value" : "http://dbpedia.org/resource/Tour_of_Duty_(TV_series)" } ] } ,  "http://dbpedia.org/resource/Military_Assistance_Command,_Vietnam_\u2013_Studies_and_Observations_Group" : { "http://dbpedia.org/ontology/wikiPageWikiLink" : [ { "type" : "uri", "value" : "http://dbpedia.org/resource/Tour_of_Duty_(TV_series)" } ] } ,  "http://dbpedia.org/resource/Tony_Carreiro" : { "http://dbpedia.org/ontology/wikiPageWikiLink" : [ { "type" : "uri", "value" : "http://dbpedia.org/resource/Tour_of_Duty_(TV_series)" } ] } ,  "http://dbpedia.org/resource/Betsy_Brantley" : { "http://dbpedia.org/ontology/wikiPageWikiLink" : [ { "type" : "uri", "value" : "http://dbpedia.org/resource/Tour_of_Duty_(TV_series)" } ] } ,  "http://dbpedia.org/resource/TRT_2" : { "http://dbpedia.org/ontology/wikiPageWikiLink" : [ { "type" : "uri", "value" : "http://dbpedia.org/resource/Tour_of_Duty_(TV_series)" } ] } ,  "http://dbpedia.org/resource/Conflict:_Vietnam" : { "http://dbpedia.org/ontology/wikiPageWikiLink" : [ { "type" : "uri", "value" : "http://dbpedia.org/resource/Tour_of_Duty_(TV_series)" } ] } ,  "http://dbpedia.org/resource/Film_and_television_in_Hawaii" : { "http://dbpedia.org/ontology/wikiPageWikiLink" : [ { "type" : "uri", "value" : "http://dbpedia.org/resource/Tour_of_Duty_(TV_series)" } ] } ,  "http://dbpedia.org/resource/List_of_programs_broadcast_by_TVNorge" : { "http://dbpedia.org/ontology/wikiPageWikiLink" : [ { "type" : "uri", "value" : "http://dbpedia.org/resource/Tour_of_Duty_(TV_series)" } ] } ,  "http://dbpedia.org/resource/Ren_Hanami" : { "http://dbpedia.org/ontology/wikiPageWikiLink" : [ { "type" : "uri", "value" : "http://dbpedia.org/resource/Tour_of_Duty_(TV_series)" } ] } ,  "http://dbpedia.org/resource/China_Beach" : { "http://dbpedia.org/ontology/wikiPageWikiLink" : [ { "type" : "uri", "value" : "http://dbpedia.org/resource/Tour_of_Duty_(TV_series)" } ] } ,  "http://dbpedia.org/resource/Saudi_2" : { "http://dbpedia.org/ontology/wikiPageWikiLink" : [ { "type" : "uri", "value" : "http://dbpedia.org/resource/Tour_of_Duty_(TV_series)" } ] } ,  "http://dbpedia.org/resource/Rick_Husky" : { "http://dbpedia.org/ontology/wikiPageWikiLink" : [ { "type" : "uri", "value" : "http://dbpedia.org/resource/Tour_of_Duty_(TV_series)" } ] } ,  "http://dbpedia.org/resource/James_Pax" : { "http://dbpedia.org/ontology/wikiPageWikiLink" : [ { "type" : "uri", "value" : "http://dbpedia.org/resource/Tour_of_Duty_(TV_series)" } ] } ,  "http://dbpedia.org/resource/Robert_Fuller_(actor)" : { "http://dbpedia.org/ontology/wikiPageWikiLink" : [ { "type" : "uri", "value" : "http://dbpedia.org/resource/Tour_of_Duty_(TV_series)" } ] } ,  "http://dbpedia.org/resource/John_Kassir" : { "http://dbpedia.org/ontology/wikiPageWikiLink" : [ { "type" : "uri", "value" : "http://dbpedia.org/resource/Tour_of_Duty_(TV_series)" } ] } ,  "http://dbpedia.org/resource/Leo_Rossi" : { "http://dbpedia.org/ontology/wikiPageWikiLink" : [ { "type" : "uri", "value" : "http://dbpedia.org/resource/Tour_of_Duty_(TV_series)" } ] } ,  "http://dbpedia.org/resource/Lar_Park_Lincoln" : { "http://dbpedia.org/ontology/wikiPageWikiLink" : [ { "type" : "uri", "value" : "http://dbpedia.org/resource/Tour_of_Duty_(TV_series)" } ] } ,  "http://dbpedia.org/resource/Martha_Vel\u00E9z" : { "http://dbpedia.org/ontology/wikiPageWikiLink" : [ { "type" : "uri", "value" : "http://dbpedia.org/resource/Tour_of_Duty_(TV_series)" } ] } ,  "http://dbpedia.org/resource/Tour_of_Duty_(season_3)" : { "http://dbpedia.org/ontology/wikiPageWikiLink" : [ { "type" : "uri", "value" : "http://dbpedia.org/resource/Tour_of_Duty_(TV_series)" } ] } ,  "http://dbpedia.org/resource/Antoni_Stutz" : { "http://dbpedia.org/ontology/wikiPageWikiLink" : [ { "type" : "uri", "value" : "http://dbpedia.org/resource/Tour_of_Duty_(TV_series)" } ] } ,  "http://dbpedia.org/resource/John_Shepherd_(actor)" : { "http://dbpedia.org/ontology/wikiPageWikiLink" : [ { "type" : "uri", "value" : "http://dbpedia.org/resource/Tour_of_Duty_(TV_series)" } ] } ,  "http://dbpedia.org/resource/Joshua_D._Maurer" : { "http://dbpedia.org/ontology/wikiPageWikiLink" : [ { "type" : "uri", "value" : "http://dbpedia.org/resource/Tour_of_Duty_(TV_series)" } ] } ,  "http://dbpedia.org/resource/Julie_Ow" : { "http://dbpedia.org/ontology/wikiPageWikiLink" : [ { "type" : "uri", "value" : "http://dbpedia.org/resource/Tour_of_Duty_(TV_series)" } ] } ,  "http://dbpedia.org/resource/Tour_of_Duty_(season_1)" : { "http://dbpedia.org/ontology/wikiPageWikiLink" : [ { "type" : "uri", "value" : "http://dbpedia.org/resource/Tour_of_Duty_(TV_series)" } ] } ,  "http://dbpedia.org/resource/Kim_Delaney" : { "http://dbpedia.org/ontology/wikiPageWikiLink" : [ { "type" : "uri", "value" : "http://dbpedia.org/resource/Tour_of_Duty_(TV_series)" } ] } ,  "http://dbpedia.org/resource/List_of_programs_broadcast_by_Network_10" : { "http://dbpedia.org/ontology/wikiPageWikiLink" : [ { "type" : "uri", "value" : "http://dbpedia.org/resource/Tour_of_Duty_(TV_series)" } ] } ,  "http://dbpedia.org/resource/List_of_programs_previously_broadcast_by_GMA_Network" : { "http://dbpedia.org/ontology/wikiPageWikiLink" : [ { "type" : "uri", "value" : "http://dbpedia.org/resource/Tour_of_Duty_(TV_series)" } ] } ,  "http://dbpedia.org/resource/Tour_of_duty_(disambiguation)" : { "http://dbpedia.org/ontology/wikiPageWikiLink" : [ { "type" : "uri", "value" : "http://dbpedia.org/resource/Tour_of_Duty_(TV_series)" } ] ,    "http://dbpedia.org/ontology/wikiPageDisambiguates" : [ { "type" : "uri", "value" : "http://dbpedia.org/resource/Tour_of_Duty_(TV_series)" } ] } ,  "http://dbpedia.org/resource/I_Got_You_(I_Feel_Good)" : { "http://dbpedia.org/ontology/wikiPageWikiLink" : [ { "type" : "uri", "value" : "http://dbpedia.org/resource/Tour_of_Duty_(TV_series)" } ] } ,  "http://dbpedia.org/resource/L._Scott_Caldwell" : { "http://dbpedia.org/ontology/wikiPageWikiLink" : [ { "type" : "uri", "value" : "http://dbpedia.org/resource/Tour_of_Duty_(TV_series)" } ] } ,  "http://dbpedia.org/resource/1960_in_television" : { "http://dbpedia.org/ontology/wikiPageWikiLink" : [ { "type" : "uri", "value" : "http://dbpedia.org/resource/Tour_of_Duty_(TV_series)" } ] } ,  "http://dbpedia.org/resource/Glenn_Plummer" : { "http://dbpedia.org/ontology/wikiPageWikiLink" : [ { "type" : "uri", "value" : "http://dbpedia.org/resource/Tour_of_Duty_(TV_series)" } ] } ,  "http://dbpedia.org/resource/William_Sadler_(actor)" : { "http://dbpedia.org/ontology/wikiPageWikiLink" : [ { "type" : "uri", "value" : "http://dbpedia.org/resource/Tour_of_Duty_(TV_series)" } ] } ,  "http://dbpedia.org/resource/Ving_Rhames" : { "http://dbpedia.org/ontology/wikiPageWikiLink" : [ { "type" : "uri", "value" : "http://dbpedia.org/resource/Tour_of_Duty_(TV_series)" } ] } ,  "http://dbpedia.org/resource/Kamala_Lopez" : { "http://dbpedia.org/ontology/wikiPageWikiLink" : [ { "type" : "uri", "value" : "http://dbpedia.org/resource/Tour_of_Duty_(TV_series)" } ] } ,  "http://dbpedia.org/resource/Clifton_Powell" : { "http://dbpedia.org/ontology/wikiPageWikiLink" : [ { "type" : "uri", "value" : "http://dbpedia.org/resource/Tour_of_Duty_(TV_series)" } ] } ,  "http://dbpedia.org/resource/Bruce_Gray" : { "http://dbpedia.org/ontology/wikiPageWikiLink" : [ { "type" : "uri", "value" : "http://dbpedia.org/resource/Tour_of_Duty_(TV_series)" } ] } ,  "http://dbpedia.org/resource/Melora_Hardin" : { "http://dbpedia.org/ontology/wikiPageWikiLink" : [ { "type" : "uri", "value" : "http://dbpedia.org/resource/Tour_of_Duty_(TV_series)" } ] } ,  "http://dbpedia.org/resource/Tina_Lifford" : { "http://dbpedia.org/ontology/wikiPageWikiLink" : [ { "type" : "uri", "value" : "http://dbpedia.org/resource/Tour_of_Duty_(TV_series)" } ] } ,  "http://dbpedia.org/resource/John_DeMita" : { "http://dbpedia.org/ontology/wikiPageWikiLink" : [ { "type" : "uri", "value" : "http://dbpedia.org/resource/Tour_of_Duty_(TV_series)" } ] } ,  "http://dbpedia.org/resource/Kyle_Chandler" : { "http://dbpedia.org/ontology/wikiPageWikiLink" : [ { "type" : "uri", "value" : "http://dbpedia.org/resource/Tour_of_Duty_(TV_series)" } ] } ,  "http://dbpedia.org/resource/Fran\u00E7ois_Chau" : { "http://dbpedia.org/ontology/wikiPageWikiLink" : [ { "type" : "uri", "value" : "http://dbpedia.org/resource/Tour_of_Duty_(TV_series)" } ] } ,  "http://dbpedia.org/resource/Miguel_A._N\u00FA\u00F1ez_Jr." : { "http://dbpedia.org/ontology/wikiPageWikiLink" : [ { "type" : "uri", "value" : "http://dbpedia.org/resource/Tour_of_Duty_(TV_series)" } ] } ,  "http://dbpedia.org/resource/Jon_Gries" : { "http://dbpedia.org/ontology/wikiPageWikiLink" : [ { "type" : "uri", "value" : "http://dbpedia.org/resource/Tour_of_Duty_(TV_series)" } ] } ,  "http://dbpedia.org/resource/Carl_Weathers" : { "http://dbpedia.org/ontology/wikiPageWikiLink" : [ { "type" : "uri", "value" : "http://dbpedia.org/resource/Tour_of_Duty_(TV_series)" } ] } ,  "http://dbpedia.org/resource/Jim_Piddock" : { "http://dbpedia.org/ontology/wikiPageWikiLink" : [ { "type" : "uri", "value" : "http://dbpedia.org/resource/Tour_of_Duty_(TV_series)" } ] } ,  "http://dbpedia.org/resource/List_of_Sony_Pictures_Television_programs" : { "http://dbpedia.org/ontology/wikiPageWikiLink" : [ { "type" : "uri", "value" : "http://dbpedia.org/resource/Tour_of_Duty_(TV_series)" } ] } ,  "http://dbpedia.org/resource/Olivia_d'Abo" : { "http://dbpedia.org/ontology/wikiPageWikiLink" : [ { "type" : "uri", "value" : "http://dbpedia.org/resource/Tour_of_Duty_(TV_series)" } ] } ,  "http://dbpedia.org/resource/Rosalind_Chao" : { "http://dbpedia.org/ontology/wikiPageWikiLink" : [ { "type" : "uri", "value" : "http://dbpedia.org/resource/Tour_of_Duty_(TV_series)" } ] } ,  "http://dbpedia.org/resource/1987_in_American_television" : { "http://dbpedia.org/ontology/wikiPageWikiLink" : [ { "type" : "uri", "value" : "http://dbpedia.org/resource/Tour_of_Duty_(TV_series)" } ] } ,  "http://dbpedia.org/resource/Ronald_L._Schwary" : { "http://dbpedia.org/ontology/wikiPageWikiLink" : [ { "type" : "uri", "value" : "http://dbpedia.org/resource/Tour_of_Duty_(TV_series)" } ] } ,  "http://dbpedia.org/resource/Viewers_for_Quality_Television" : { "http://dbpedia.org/ontology/wikiPageWikiLink" : [ { "type" : "uri", "value" : "http://dbpedia.org/resource/Tour_of_Duty_(TV_series)" } ] } ,  "http://dbpedia.org/resource/List_of_South_African_television_series" : { "http://dbpedia.org/ontology/wikiPageWikiLink" : [ { "type" : "uri", "value" : "http://dbpedia.org/resource/Tour_of_Duty_(TV_series)" } ] } ,  "http://dbpedia.org/resource/Tri-Cities,_Washington" : { "http://dbpedia.org/ontology/wikiPageWikiLink" : [ { "type" : "uri", "value" : "http://dbpedia.org/resource/Tour_of_Duty_(TV_series)" } ] } ,  "http://dbpedia.org/resource/Joe_Moore_(television_journalist)" : { "http://dbpedia.org/ontology/wikiPageWikiLink" : [ { "type" : "uri", "value" : "http://dbpedia.org/resource/Tour_of_Duty_(TV_series)" } ] } ,  "http://dbpedia.org/resource/A_Whiter_Shade_of_Pale" : { "http://dbpedia.org/ontology/wikiPageWikiLink" : [ { "type" : "uri", "value" : "http://dbpedia.org/resource/Tour_of_Duty_(TV_series)" } ] } ,  "http://dbpedia.org/resource/Leilani_Sarelle" : { "http://dbpedia.org/ontology/wikiPageWikiLink" : [ { "type" : "uri", "value" : "http://dbpedia.org/resource/Tour_of_Duty_(TV_series)" } ] } ,  "http://dbpedia.org/resource/American_Cinema_Editors_Award_for_Best_Edited_Comedy_Series_for_Commercial_Television" : { "http://dbpedia.org/ontology/wikiPageWikiLink" : [ { "type" : "uri", "value" : "http://dbpedia.org/resource/Tour_of_Duty_(TV_series)" } ] } ,  "http://dbpedia.org/resource/American_Cinema_Editors_Award_for_Best_Edited_Comedy_Series_for_Non-Commercial_Television" : { "http://dbpedia.org/ontology/wikiPageWikiLink" : [ { "type" : "uri", "value" : "http://dbpedia.org/resource/Tour_of_Duty_(TV_series)" } ] } ,  "http://dbpedia.org/resource/American_Cinema_Editors_Award_for_Best_Edited_Drama_Series_for_Commercial_Television" : { "http://dbpedia.org/ontology/wikiPageWikiLink" : [ { "type" : "uri", "value" : "http://dbpedia.org/resource/Tour_of_Duty_(TV_series)" } ] } ,  "http://dbpedia.org/resource/American_Cinema_Editors_Award_for_Best_Edited_Drama_Series_for_Non-Commercial_Television" : { "http://dbpedia.org/ontology/wikiPageWikiLink" : [ { "type" : "uri", "value" : "http://dbpedia.org/resource/Tour_of_Duty_(TV_series)" } ] } ,  "http://dbpedia.org/resource/Primetime_Emmy_Award_for_Outstanding_Sound_Mixing_for_a_Comedy_or_Drama_Series_(One-Hour)" : { "http://dbpedia.org/ontology/wikiPageWikiLink" : [ { "type" : "uri", "value" : "http://dbpedia.org/resource/Tour_of_Duty_(TV_series)" } ] } ,  "http://dbpedia.org/resource/List_of_United_States_Christmas_television_episodes" : { "http://dbpedia.org/ontology/wikiPageWikiLink" : [ { "type" : "uri", "value" : "http://dbpedia.org/resource/Tour_of_Duty_(TV_series)" } ] } ,  "http://dbpedia.org/resource/List_of_programs_broadcast_by_CBS" : { "http://dbpedia.org/ontology/wikiPageWikiLink" : [ { "type" : "uri", "value" : "http://dbpedia.org/resource/Tour_of_Duty_(TV_series)" } ] } ,  "http://dbpedia.org/resource/1990_in_American_television" : { "http://dbpedia.org/ontology/wikiPageWikiLink" : [ { "type" : "uri", "value" : "http://dbpedia.org/resource/Tour_of_Duty_(TV_series)" } ] } ,  "http://dbpedia.org/resource/1990\u201391_United_States_network_television_schedule" : { "http://dbpedia.org/ontology/wikiPageWikiLink" : [ { "type" : "uri", "value" : "http://dbpedia.org/resource/Tour_of_Duty_(TV_series)" } ] } ,  "http://dbpedia.org/resource/1966_in_television" : { "http://dbpedia.org/ontology/wikiPageWikiLink" : [ { "type" : "uri", "value" : "http://dbpedia.org/resource/Tour_of_Duty_(TV_series)" } ] } ,  "http://dbpedia.org/resource/1987\u201388_United_States_network_television_schedule" : { "http://dbpedia.org/ontology/wikiPageWikiLink" : [ { "type" : "uri", "value" : "http://dbpedia.org/resource/Tour_of_Duty_(TV_series)" } ] } ,  "http://dbpedia.org/resource/Stephen_Caffrey_(actor)" : { "http://dbpedia.org/ontology/wikiPageWikiLink" : [ { "type" : "uri", "value" : "http://dbpedia.org/resource/Tour_of_Duty_(TV_series)" } ] } ,  "http://dbpedia.org/resource/Zev_Braun" : { "http://dbpedia.org/ontology/wikiPageWikiLink" : [ { "type" : "uri", "value" : "http://dbpedia.org/resource/Tour_of_Duty_(TV_series)" } ] } ,  "http://dbpedia.org/resource/1959_in_television" : { "http://dbpedia.org/ontology/wikiPageWikiLink" : [ { "type" : "uri", "value" : "http://dbpedia.org/resource/Tour_of_Duty_(TV_series)" } ] } ,  "http://dbpedia.org/resource/1963_in_television" : { "http://dbpedia.org/ontology/wikiPageWikiLink" : [ { "type" : "uri", "value" : "http://dbpedia.org/resource/Tour_of_Duty_(TV_series)" } ] } ,  "http://dbpedia.org/resource/1964_in_television" : { "http://dbpedia.org/ontology/wikiPageWikiLink" : [ { "type" : "uri", "value" : "http://dbpedia.org/resource/Tour_of_Duty_(TV_series)" } ] } ,  "http://dbpedia.org/resource/Tony_Becker" : { "http://dbpedia.org/ontology/wikiPageWikiLink" : [ { "type" : "uri", "value" : "http://dbpedia.org/resource/Tour_of_Duty_(TV_series)" } ] } ,  "http://dbpedia.org/resource/Dan_Gauthier" : { "http://dbpedia.org/ontology/wikiPageWikiLink" : [ { "type" : "uri", "value" : "http://dbpedia.org/resource/Tour_of_Duty_(TV_series)" } ] } ,  "http://dbpedia.org/resource/Greg_Germann" : { "http://dbpedia.org/ontology/wikiPageWikiLink" : [ { "type" : "uri", "value" : "http://dbpedia.org/resource/Tour_of_Duty_(TV_series)" } ] } ,  "http://dbpedia.org/resource/Helaine_Head" : { "http://dbpedia.org/ontology/wikiPageWikiLink" : [ { "type" : "uri", "value" : "http://dbpedia.org/resource/Tour_of_Duty_(TV_series)" } ] } ,  "http://dbpedia.org/resource/Marietta_DePrima" : { "http://dbpedia.org/ontology/wikiPageWikiLink" : [ { "type" : "uri", "value" : "http://dbpedia.org/resource/Tour_of_Duty_(TV_series)" } ] } ,  "http://dbpedia.org/resource/1946_in_television" : { "http://dbpedia.org/ontology/wikiPageWikiLink" : [ { "type" : "uri", "value" : "http://dbpedia.org/resource/Tour_of_Duty_(TV_series)" } ] } ,  "http://dbpedia.org/resource/196th_Infantry_Brigade_(United_States)" : { "http://dbpedia.org/ontology/wikiPageWikiLink" : [ { "type" : "uri", "value" : "http://dbpedia.org/resource/Tour_of_Duty_(TV_series)" } ] } ,  "http://dbpedia.org/resource/Wally_Taylor_(actor)" : { "http://dbpedia.org/ontology/wikiPageWikiLink" : [ { "type" : "uri", "value" : "http://dbpedia.org/resource/Tour_of_Duty_(TV_series)" } ] } ,  "http://dbpedia.org/resource/James_Hong_filmography" : { "http://dbpedia.org/ontology/wikiPageWikiLink" : [ { "type" : "uri", "value" : "http://dbpedia.org/resource/Tour_of_Duty_(TV_series)" } ] } ,  "http://dbpedia.org/resource/Fox_Classics" : { "http://dbpedia.org/ontology/wikiPageWikiLink" : [ { "type" : "uri", "value" : "http://dbpedia.org/resource/Tour_of_Duty_(TV_series)" } ] } ,  "http://dbpedia.org/resource/Fran_Bennett" : { "http://dbpedia.org/ontology/wikiPageWikiLink" : [ { "type" : "uri", "value" : "http://dbpedia.org/resource/Tour_of_Duty_(TV_series)" } ] } ,  "http://dbpedia.org/resource/Sherry_Hursey" : { "http://dbpedia.org/ontology/wikiPageWikiLink" : [ { "type" : "uri", "value" : "http://dbpedia.org/resource/Tour_of_Duty_(TV_series)" } ] } ,  "http://dbpedia.org/resource/David_Kemper_(writer)" : { "http://dbpedia.org/ontology/wikiPageWikiLink" : [ { "type" : "uri", "value" : "http://dbpedia.org/resource/Tour_of_Duty_(TV_series)" } ] } ,  "http://dbpedia.org/resource/Paul_Lynch_(director)" : { "http://dbpedia.org/ontology/wikiPageWikiLink" : [ { "type" : "uri", "value" : "http://dbpedia.org/resource/Tour_of_Duty_(TV_series)" } ] } ,  "http://dbpedia.org/resource/Eddie_Velez" : { "http://dbpedia.org/ontology/wikiPageWikiLink" : [ { "type" : "uri", "value" : "http://dbpedia.org/resource/Tour_of_Duty_(TV_series)" } ] } ,  "http://dbpedia.org/resource/Kristoffer_Tabori" : { "http://dbpedia.org/ontology/wikiPageWikiLink" : [ { "type" : "uri", "value" : "http://dbpedia.org/resource/Tour_of_Duty_(TV_series)" } ] } ,  "http://dbpedia.org/resource/Angela_Bassett_filmography" : { "http://dbpedia.org/ontology/wikiPageWikiLink" : [ { "type" : "uri", "value" : "http://dbpedia.org/resource/Tour_of_Duty_(TV_series)" } ] } ,  "http://dbpedia.org/resource/Kimiko_Gelman" : { "http://dbpedia.org/ontology/wikiPageWikiLink" : [ { "type" : "uri", "value" : "http://dbpedia.org/resource/Tour_of_Duty_(TV_series)" } ] } ,  "http://dbpedia.org/resource/Robert_Knepper" : { "http://dbpedia.org/ontology/wikiPageWikiLink" : [ { "type" : "uri", "value" : "http://dbpedia.org/resource/Tour_of_Duty_(TV_series)" } ] } ,  "http://dbpedia.org/resource/Shawn_Levy" : { "http://dbpedia.org/ontology/wikiPageWikiLink" : [ { "type" : "uri", "value" : "http://dbpedia.org/resource/Tour_of_Duty_(TV_series)" } ] } ,  "http://dbpedia.org/resource/List_of_programs_broadcast_by_Middle_East_Television" : { "http://dbpedia.org/ontology/wikiPageWikiLink" : [ { "type" : "uri", "value" : "http://dbpedia.org/resource/Tour_of_Duty_(TV_series)" } ] } ,  "http://dbpedia.org/resource/Sky_5" : { "http://dbpedia.org/ontology/wikiPageWikiLink" : [ { "type" : "uri", "value" : "http://dbpedia.org/resource/Tour_of_Duty_(TV_series)" } ] } ,  "http://dbpedia.org/resource/List_of_programs_broadcast_by_TNT_(American_TV_network)" : { "http://dbpedia.org/ontology/wikiPageWikiLink" : [ { "type" : "uri", "value" : "http://dbpedia.org/resource/Tour_of_Duty_(TV_series)" } ] } ,  "http://dbpedia.org/resource/KTV2" : { "http://dbpedia.org/ontology/wikiPageWikiLink" : [ { "type" : "uri", "value" : "http://dbpedia.org/resource/Tour_of_Duty_(TV_series)" } ] } ,  "http://dbpedia.org/resource/FBC_TV" : { "http://dbpedia.org/ontology/wikiPageWikiLink" : [ { "type" : "uri", "value" : "http://dbpedia.org/resource/Tour_of_Duty_(TV_series)" } ] } ,  "http://dbpedia.org/resource/List_of_television_programs:_T" : { "http://dbpedia.org/ontology/wikiPageWikiLink" : [ { "type" : "uri", "value" : "http://dbpedia.org/resource/Tour_of_Duty_(TV_series)" } ] } ,  "http://dbpedia.org/resource/Acceptable_loss_(disambiguation)" : { "http://dbpedia.org/ontology/wikiPageWikiLink" : [ { "type" : "uri", "value" : "http://dbpedia.org/resource/Tour_of_Duty_(TV_series)" } ] }}